Workbook

Sheet Data
A1: Financial Statement Analysis Package (FSAP): Version 9.0
A2: Financial Reporting, Financial Statement Analysis, and Valuation: A Strategic Perspective, 9th Edition | I2: FSAP User Guides:
A3: By Jim Wahlen, Steve Baginski and Mark Bradshaw
I4: The FSAP user should only enter data in the blue-font cells shaded light green.
A6: The FSAP User Guides appear in column I to the right. | I6: The Data spreadsheet is designed for up to six years of financial statement data. The user must input the most recent year of financial statement data in column G, regardless of the number of years of data inputted.
I7: The user must conform financial statement data to the FSAP template because the spreadsheets within FSAP use the Data spreadsheet as their base. The user can, however, rename account titles as necessary to match the account titles of the particular firm. FSAP contains a number of general purpose accounts that can be renamed to fit the accounts of the particular firm (for example, Other Current Assets (1) and (2)).
I8: FSAP automatically computes the amounts of various sub-totals and totals within the Data spreadsheet. These items are shaded in gray and serve in checking the mathematical accuracy of inputted amounts. FSAP checks to ensure that total assets equal total liabilities and shareholders’ equity, that total revenues and gains minus total expenses and losses equal reported net income, and that cash flows from operating, investing, and financing activities equal the change in cash on the balance sheet. These financial data checks appear at the bottom of the Data spreadsheet. Any material non-zero amounts (that are not due to rounding) on these rows require the user to re-check amounts inputted to identify and correct the error.
A9: Analyst Name: | B9: Wahlen, Baginski & Bradshaw | I9: Insert your name in column B.
A10: Company Name: | B10: Starbucks | I10: Enter the name of the company in Column B. This name will appear on the output of all spreadsheets within FSAP.
A11: Year (Most recent in far right column.) | B11: 2010 | C11: 2011 | D11: 2012 | E11: 2013 | F11: 2014 | G11: 2015 | I11: Throughout FSAP, enter amounts for account titles listed in brackets <> as negative numbers. Except for per share amounts, be consistent with the units of the amounts entered (for example, thosands or millions).
A14: BALANCE SHEET DATA | I14: Enter Balance Sheet Data:
A15: Assets:
A16: Cash and cash equivalents | B16: 1164 | C16: 1148.1 | D16: 1188.6 | E16: 2575.7 | F16: 1708.4 | G16: 1530.1
A17: Short-term investments | B17: 285.7 | C17: 902.6 | D17: 848.4 | E17: 658.1 | F17: 135.4 | G17: 81.3
A18: Accounts and notes receivable - net | B18: 302.7 | C18: 386.5 | D18: 485.9 | E18: 561.4 | F18: 631 | G18: 719
A19: Inventories | B19: 543.3 | C19: 965.8 | D19: 1241.5 | E19: 1111.2 | F19: 1090.9 | G19: 1306.4
A20: Prepaid expenses and other current assets | B20: 156.5 | C20: 161.5 | D20: 196.5 | E20: 287.7 | F20: 285.6 | G20: 334.2
A21: Deferred income taxes - current | B21: 304.2 | C21: 230.4 | D21: 238.7 | E21: 277.3 | F21: 317.4 | G21: 381.77
A22: Other current assets (1) | I22: Other current assets (1) and (2) can be renamed and used for different types of current assets for different firms.
A23: Other current assets (2)
A24: Current Assets | B24: =SUM(B16:B23) -> 2756.4 | C24: =SUM(C16:C23) -> 3794.9 | D24: =SUM(D16:D23) -> 4199.6 | E24: =SUM(E16:E23) -> 5471.4 | F24: =SUM(F16:F23) -> 4168.7 | G24: =SUM(G16:G23) -> 4352.77 | I24: FSAP automatically computes the amount of total current assets.
A25: Long-term investments | B25: 191.8 | C25: 107 | D25: 116 | E25: 58.3 | F25: 318.4 | G25: 312.5
A26: Equity and cost investments | B26: 341.5 | C26: 372.3 | D26: 459.9 | E26: 496.5 | F26: 514.9 | G26: 352
A27: Property, plant, and equipment - at cost | B27: 5888.7 | C27: 6163.1 | D27: 6903.1 | E27: 7782.1 | F27: 8581.1 | G27: 9641.8
A28: <Accumulated depreciation> | B28: -3472.2 | C28: -3808.1 | D28: -4244.2 | E28: -4581.6 | F28: -5062.1 | G28: -5553.5
A29: Deferred income taxes - noncurrent | B29: 195.3 | C29: 156.3 | D29: 97.3 | E29: 967 | F29: 903.3 | G29: 828.9
A30: Other assets | B30: 151.2 | C30: 141.4 | D30: 144.7 | E30: =185.3 -> 185.3 | F30: =198.9 -> 198.9 | G30: =415.9 -> 415.9
A31: Other intangible assets | B31: 70.8 | C31: 111.9 | D31: 143.7 | E31: 274.8 | F31: 273.5 | G31: =302.5+217.9 -> 520.4
A32: Goodwill | B32: 262.4 | C32: 321.6 | D32: =399.1 -> 399.1 | E32: =862.9 -> 862.9 | F32: =856.2 -> 856.2 | G32: =1575.4 -> 1575.4
A33: Total Assets | B33: =SUM(B24:B32) -> 6385.9 | C33: =SUM(C24:C32) -> 7360.4 | D33: =SUM(D24:D32) -> 8219.2 | E33: =SUM(E24:E32) -> 11516.7 | F33: =SUM(F24:F32) -> 10752.9 | G33: =SUM(G24:G32) -> 12446.17 | I33: FSAP automatically computes the amount of total assets.
A35: Liabilities and Equities:
A36: Accounts payable | B36: 282.6 | C36: 540 | D36: 398.1 | E36: 491.7 | F36: 533.7 | G36: 684.2
A37: Accrued liabilities | B37: 936.2 | C37: 940.9 | D37: 1133.8 | E37: 1269.3 | F37: 1514.4 | G37: 1760.7
A38: Notes payable and short-term debt
A39: Current maturities of long-term debt
A40: Deferred tax liabilities - current
A41: Insurance Reserves | B41: 146.2 | C41: 145.6 | D41: 167.7 | E41: 178.5 | F41: 196.1 | G41: 224.8 | I41: Other current liabilities (1) and (2) can be renamed and used for different types of current liabilities for different firms.
A42: Stored value card liability | B42: 414.1 | C42: 449.3 | D42: 510.2 | E42: 653.7 | F42: 794.5 | G42: 983.8
A43: Accrued litigation charge | E43: 2784.1
A44: Current Liabilities | B44: =SUM(B36:B43) -> 1779.1 | C44: =SUM(C36:C43) -> 2075.8 | D44: =SUM(D36:D43) -> 2209.8 | E44: =SUM(E36:E43) -> 5377.3 | F44: =SUM(F36:F43) -> 3038.7 | G44: =SUM(G36:G43) -> 3653.5 | I44: FSAP automatically computes the amount of total current liabilities.
A45: Long-term debt | B45: 549.4 | C45: 549.5 | D45: 549.6 | E45: 1299.4 | F45: 2048.3 | G45: 2347.5
A46: Long-term accrued liabilities | B46: 375.1 | C46: 347.8 | D46: 345.3 | E46: 357.7 | F46: 392.2 | G46: 625.3
A47: Deferred tax liabilities- noncurrent
A48: Other noncurrent liabilities (1) | I48: Other noncurrent liabilities (1) and (2) can be renamed and used for different types of non-current liabilities for different firms.
A49: Other noncurrent liabilities (2)
A50: Total Liabilities | B50: =SUM(B44:B49) -> 2703.6 | C50: =SUM(C44:C49) -> 2973.1 | D50: =SUM(D44:D49) -> 3104.7 | E50: =SUM(E44:E49) -> 7034.4 | F50: =SUM(F44:F49) -> 5479.2 | G50: =SUM(G44:G49) -> 6626.3 | I50: FSAP automatically computes the amount of total liabilitries.
A52: Preferred stock
A53: Common stock + Additional paid in capital | B53: 146.3 | C53: 41.2 | D53: 40.1 | E53: 282.9 | F53: 40.1 | G53: 42.6
A54: Retained earnings <deficit> | B54: 3471.2 | C54: 4297.4 | D54: 5046.2 | E54: 4130.3 | F54: 5206.6 | G54: 5974.8
A55: Accum. other comprehensive income <loss> | B55: 57.2 | C55: 46.3 | D55: 22.7 | E55: 67 | F55: 25.3 | G55: -199.4 | I55: The amount for this item appears either on the Balance Sheet or the Statement of Shareholders' Equity. Be sure to enter as a positive or negative amount as appropriate.
A56: <Treasury stock> and other equity adjustments | I56: Include on this line any treasury stock accounts and any items that do not fall within some other shareholders' equity line. Such items seldom appear in balance sheets of U.S. firms. Amounts that increase (decrease) total shareholders' equity should be entered as positive (negative) amounts.
A57: Total Common Shareholders' Equity | B57: =SUM(B53:B56) -> 3674.7 | C57: =SUM(C53:C56) -> 4384.9 | D57: =SUM(D53:D56) -> 5109 | E57: =SUM(E53:E56) -> 4480.2 | F57: =SUM(F53:F56) -> 5272 | G57: =SUM(G53:G56) -> 5818 | I57: FSAP automatically computes the amount of total shareholders' equity.
A58: Noncontrolling interests | B58: 7.6 | C58: 2.4 | D58: 5.5 | E58: 2.1 | F58: 1.7 | G58: 1.8
A59: Total Equity | B59: =B52+B57+B58 -> 3682.3 | C59: =C52+C57+C58 -> 4387.3 | D59: =D52+D57+D58 -> 5114.5 | E59: =E52+E57+E58 -> 4482.3 | F59: =F52+F57+F58 -> 5273.7 | G59: =G52+G57+G58 -> 5819.8
A60: Total Liabilities and Equities | B60: =B50+B59 -> 6385.9 | C60: =C50+C59 -> 7360.4 | D60: =D50+D59 -> 8219.2 | E60: =E50+E59 -> 11516.7 | F60: =F50+F59 -> 10752.9 | G60: =G50+G59 -> 12446.1 | I60: FSAP automatically computes the amount of total liabilities plus shareholders' equity.
A63: INCOME STATEMENT DATA | B63: =B11 -> 2010 | C63: =C11 -> 2011 | D63: =D11 -> 2012 | E63: =E11 -> 2013 | F63: =F11 -> 2014 | G63: =G11 -> 2015 | I63: Enter Income Statement Data:
I64: When entering income statement data, enter amounts that increase income (revenues, gains, income) as positive amounts, and enter amounts that decrease income (expenses, losses) as negative amounts.
A65: Revenues | B65: 10707.4 | C65: 11700.4 | D65: 13299.5 | E65: 14866.8 | F65: 16447.8 | G65: 19162.7
A66: <Cost of sales and occupancy expense> | B66: -4458.6 | C66: -4949.3 | D66: -5813.3 | E66: -6382.3 | F66: -6858.8 | G66: -7787.5
A67: Gross Profit | B67: =B65+B66 -> 6248.8 | C67: =C65+C66 -> 6751.1 | D67: =D65+D66 -> 7486.2 | E67: =E65+E66 -> 8484.5 | F67: =F65+F66 -> 9589 | G67: =G65+G66 -> 11375.2 | I67: FSAP automatically computes the amount of gross profit.
A68: <Store Operating Expenses> | B68: -3551.4 | C68: -3665.1 | D68: -3918.1 | E68: -4286.1 | F68: -4638.2 | G68: -5411.1
A69: <Other Operating Expenses> | B69: -293.2 | C69: -402 | D69: -429.9 | E69: -431.8 | F69: -457.3 | G69: -522.4
A70: <Depreciation and Amortization> | B70: -510.4 | C70: -523.3 | D70: -550.3 | E70: -621.4 | F70: -709.6 | G70: -893.9
A71: <General and Administrative Expenses> | B71: -569.5 | C71: -636.1 | D71: -801.2 | E71: -937.9 | F71: -991.3 | G71: -1196.7 | I71: Other operating expenses (1), (2), and (3) can be renamed and used for different types of recurring operating expenses for different firms.
A72: Other operating expenses (1)
A73: Other operating expenses (2) | I73: Other operating income (1) and (2) can be renamed used for different sources of recurring operating income for different firms.
A74: Income from Equity Investees | B74: 148.1 | C74: 173.7 | D74: 210.7 | E74: 251.4 | F74: 268.3 | G74: 249.9
A75: Non-recurring operating gains <losses> | B75: -53 | C75: 30.2 | E75: -2784.1 | F75: 20.2 | I75: The FSAP user must decide whether particular operating gains or losses are non-recurring - infrequent and unusual given the firm's business and operating environment. If so, enter the amounts on the appropriate rows. Enter expense and loss amounts as negative numbers.
A76: Operating Profit | B76: =SUM(B67:B75) -> 1419.4 | C76: =SUM(C67:C75) -> 1728.5 | D76: =SUM(D67:D75) -> 1997.4 | E76: =SUM(E67:E75) -> -325.4 | F76: =SUM(F67:F75) -> 3081.1 | G76: =SUM(G67:G75) -> 3601 | I76: FSAP automatically computes the amount of operating profit.
A77: Interest income | B77: 50.3 | C77: 115.9 | D77: 94.4 | E77: 123.6 | F77: 142.7 | G77: 43
A78: <Interest expense> | B78: -32.7 | C78: -33.3 | D78: -32.7 | E78: -28.1 | F78: -64.1 | G78: -70.5
A79: Income <Loss> from equity affiliates | I79: Enter any amounts of income (or <loss>) from equity or noncontrolled affiliates.
A80: Other income or gains <Other expenses or losses> | G80: =390.6-61.1 -> 329.5 | I80: Enter income or gain amounts (or expense or loss amounts as negative numbers) that are unusual and non-recurring and outside of normal business operations.
A81: Income before Tax | B81: =SUM(B76:B80) -> 1437 | C81: =SUM(C76:C80) -> 1811.1 | D81: =SUM(D76:D80) -> 2059.1 | E81: =SUM(E76:E80) -> -229.9 | F81: =SUM(F76:F80) -> 3159.7 | G81: =SUM(G76:G80) -> 3903 | I81: FSAP automatically computes the amount of income before tax.
A82: <Income tax expense> | B82: -488.7 | C82: -563.1 | D82: -674.4 | E82: 238.7 | F82: -1092 | G82: -1143.7 | I82: Enter the amount of income tax expense that appears on the income statement in the section for income from continuing operations. If income tax expense reduces income, enter the amount as a negative number.
A83: Income <Loss> from discontinued operations | I83: Enter any amount reported in the separate section of the income statement labeled Discontinued Operations. The amount is reported net of tax effects. Enter as a positive or negative number as appropriate.
A84: Extraordinary gains <losses> | I84: Enter any amount reported in the separate section of the income statement labeled Extraordinary Items. The amount is reported net of taxes. Enter as a positive or negative number as appropriate.
A85: Changes in accounting principles | I85: Enter any amount reported in the separate section of the income statement labeled Changes in Accounting Principles. The amount is reported net of income taxes. Enter as a positive or negative number as appropriate.
A86: Net Income | B86: =SUM(B81:B85) -> 948.3 | C86: =SUM(C81:C85) -> 1248 | D86: =SUM(D81:D85) -> 1384.7 | E86: =SUM(E81:E85) -> 8.8 | F86: =SUM(F81:F85) -> 2067.7 | G86: =SUM(G81:G85) -> 2759.3 | I86: FSAP automatically computes the amount of net income using the above data for revenues, expenses, gains and losses.
A87: Net income attributable to noncontrolling interests | B87: -2.7 | C87: -2.3 | D87: -0.9 | E87: -0.5 | F87: 0.4 | G87: -1.9 | I87: Enter the amount of net income attributable to noncontrolling interests. Enter amount as a negative number. If the firm reports a net loss attributable to noncontrolling interests, enter the amount as a positive number.
A88: Net Income attributable to common shareholders | B88: =B86+B87 -> 945.6 | C88: =C86+C87 -> 1245.7 | D88: =D86+D87 -> 1383.8 | E88: =E86+E87 -> 8.3 | F88: =F86+F87 -> 2068.1 | G88: =G86+G87 -> 2757.4
A89: Net Income (enter reported amount as a check) | B89: 945.6 | C89: 1245.7 | D89: 1383.8 | E89: 8.3 | F89: 2068.1 | G89: 2757.4 | I89: Enter the amount of reported net income on this line. It will be used by FSAP to provide a mathematical check on the amounts of all revenues and expenses on preceding lines.
A91: Other comprehensive income items | B91: -8.2 | C91: -10.9 | D91: -23.6 | E91: =44.3-0.5 -> 43.8 | F91: =-41.7+0.4 -> -41.3 | G91: =-224.7+29.2 -> -195.5 | I91: This amount usually appears in the Statement of Comprehensive Income. Enter as a positive or negative number as appropriate.
A92: Comprehensive Income | B92: =B86+B91 -> 940.1 | C92: =C86+C91 -> 1237.1 | D92: =D86+D91 -> 1361.1 | E92: =E86+E91 -> 52.6 | F92: =F86+F91 -> 2026.4 | G92: =G86+G91 -> 2563.8 | I92: FSAP automatically computes the amount of comprehensive income.
A95: STATEMENT OF CASH FLOWS DATA | B95: =B11 -> 2010 | C95: =C11 -> 2011 | D95: =D11 -> 2012 | E95: =E11 -> 2013 | F95: =F11 -> 2014 | G95: =G11 -> 2015 | I95: Enter Statement of Cash Flows Data:
I96: In the Statement of Cash Flows Data, enter amounts reported on the firm's statement of cash flows. Enter amounts that increase (decrease) cash as positive (negative) numbers. The row headings help indicate whether amounts should be positive or negative.
A97: Net Income | B97: =B86 -> 948.3 | C97: =C86 -> 1248 | D97: =D86 -> 1384.7 | E97: =E86 -> 8.8 | F97: =F86 -> 2067.7 | G97: =G86 -> 2759.3 | I97: FSAP automatically enters the Net Income amount computed above.
A98: Add back depreciation and amortization expenses | B98: 540.8 | C98: 550 | D98: 580.6 | E98: 655.6 | F98: 748.4 | G98: 933.8
A99: Add back stock-based compensation expense | B99: =113.6 -> 113.6 | C99: 145.2 | D99: 153.6 | E99: 142.3 | F99: 183.2 | G99: 209.8
A100: Deferred income taxes | B100: -42 | C100: 106.2 | D100: 61.1 | E100: -1045.9 | F100: 10.2 | G100: 21.2
A101: <Income from equity affiliates, net of dividends> | B101: -17.2 | C101: -32.9 | D101: =-49.3 -> -49.3 | E101: =-171.8+115.6 -> -56.2 | F101: =-182.7+139.2 -> -43.5 | G101: =-190.2+148.2 -> -42
A102: <Increase> Decrease in accounts receivable | B102: -33.4 | C102: -88.7 | D102: -90.3 | E102: -68.3 | F102: -79.7 | G102: -82.8
A103: <Increase> Decrease in inventories | B103: 123.2 | C103: -422.3 | D103: -273.3 | E103: 152.5 | F103: 14.3 | G103: -207.9
A104: <Increase> Decrease in prepaid expenses
A105: <Increase> Decrease in other current assets
A106: <Increase> Decrease in other noncurrent assets
A107: Increase <Decrease> in accounts payable | B107: -3.6 | C107: 227.5 | D107: -105.2 | E107: 88.7 | F107: 60.4 | G107: 137.7
A108: Increase <Decrease> in income taxes payable | E108: 298.4 | F108: 309.8 | G108: 87.6
A109: Increase <Decrease> in other current liabilities | B109: -18.7 | C109: -81.8 | D109: 23.7 | E109: 47.3 | F109: 103.9 | G109: 124.4
A110: Increase <Decrease> in deferred revenues | B110: 24.2 | C110: 35.8 | D110: 60.8 | E110: 139.9 | F110: 140.8 | G110: 170.3
...

Sheet Analysis
A1: =Data!A1 -> Financial Statement Analysis Package (FSAP): Version 9.0
A2: =Data!A2 -> Financial Reporting, Financial Statement Analysis, and Valuation: A Strategic Perspective, 9th Edition | J2: FSAP User Guides:
A3: By James Wahlen, Steve Baginski and Mark Bradshaw
A6: The FSAP User Guides appear in column J to the right. | J6: The Analysis worksheet in FSAP automatically computes a wide array of financial statement analysis ratios using the amounts entered on the Data worksheet.
J7: The FSAP User Guides next to each row provide brief descriptions of ratio computations. See the text for more in-depth discussion of how to compute and interpret each ratio.
A9: =Data!A9 -> Analyst Name: | B9: =Data!B9 -> Wahlen, Baginski & Bradshaw
A10: =Data!A10 -> Company Name: | B10: =Data!B10 -> Starbucks
A13: DATA CHECKS
A14: =Data!A154 -> Assets - Liabilities - Equities | B14: =Data!B154 -> 0 | C14: =Data!C154 -> 0 | D14: =Data!D154 -> 0 | E14: =Data!E154 -> 0 | F14: =Data!F154 -> 0 | J14: FSAP checks the Data worksheet for an equality between total assets and total liabilities plus shareholders' equity. A non-zero amount in this row indicates a likely data input error in one or more balance sheet accounts.
A15: =Data!A155 -> Net Income (computed) - Net Income (reported) | B15: =Data!B155 -> -1.0231815e-12 | C15: =Data!C155 -> 0 | D15: =Data!D155 -> 0 | E15: =Data!E155 -> -5.5777605e-13 | F15: =Data!F155 -> 0 | J15: FSAP checks whether the net income amounts determined by revenue and expense amounts entered in the Data worksheet equal the reported amount of net income. A non-zero amount on this row likely indicates an input error in one or more income statement accounts.
A16: =Data!A156 -> Cash Changes | C16: =Data!C156 -> 1.811884e-13 | D16: =Data!D156 -> -6.1106675e-13 | E16: =Data!E156 -> 0 | F16: =Data!F156 -> 0 | J16: FSAP checks that the change in cash on the statement of cash flows equals the change in cash on the balance sheet in the Data worksheet. A non-zero amount indicates either a data input error on one or more rows of the cash flow statement or the use of a different definition of cash on the two financial statements. The user should identify the reason for and correct any non-zero amount.
A17: In the computations below, a #DIV/0! message indicates that a ratio denominator is zero.
A20: PROFITABILITY FACTORS: | J20: Profitability Factors:
A21: Year | B21: =Data!$C$11 -> 2011 | C21: =Data!$D$11 -> 2012 | D21: =Data!$E$11 -> 2013 | E21: =Data!$F$11 -> 2014 | F21: =Data!$G$11 -> 2015
A23: RETURN ON ASSETS (based on reported amounts): | J23: Return on assets measures the rate of return the firm earns per average dollar invested in assets.
A24: Profit Margin for ROA | B24: =IF(ISERROR((Data!C86+(1-Data!C142)*(-Data!C78))/Data!C65),"",(Data!C86+(1-Data!C142)*(-Data!C78))/Data!C65) -> 0.10851296 | C24: =IF(ISERROR((Data!D86+(1-Data!D142)*(-Data!D78))/Data!D65),"",(Data!D86+(1-Data!D142)*(-Data!D78))/Data!D65) -> 0.10571488 | D24: =IF(ISERROR((Data!E86+(1-Data!E142)*(-Data!E78))/Data!E65),"",(Data!E86+(1-Data!E142)*(-Data!E78))/Data!E65) -> 0.0018204994 | E24: =IF(ISERROR((Data!F86+(1-Data!F142)*(-Data!F78))/Data!F65),"",(Data!F86+(1-Data!F142)*(-Data!F78))/Data!F65) -> 0.12824603 | F24: =IF(ISERROR((Data!G86+(1-Data!G142)*(-Data!G78))/Data!G65),"",(Data!G86+(1-Data!G142)*(-Data!G78))/Data!G65) -> 0.14638464 | J24: Profit margin for ROA measures how much profitability the firm derives from its revenues. For this ratio, profitability is measured before the effects of financing costs (after tax) and minority interest in earnings.
A25: x Asset Turnover | B25: =IF(ISERROR(Data!C65/((Data!B33+Data!C33)/2)),"",Data!C65/((Data!B33+Data!C33)/2)) -> 1.7023344 | C25: =IF(ISERROR(Data!D65/((Data!C33+Data!D33)/2)),"",Data!D65/((Data!C33+Data!D33)/2)) -> 1.7072967 | D25: =IF(ISERROR(Data!E65/((Data!D33+Data!E33)/2)),"",Data!E65/((Data!D33+Data!E33)/2)) -> 1.5065743 | E25: =IF(ISERROR(Data!F65/((Data!E33+Data!F33)/2)),"",Data!F65/((Data!E33+Data!F33)/2)) -> 1.4771527 | F25: =IF(ISERROR(Data!G65/((Data!F33+Data!G33)/2)),"",Data!G65/((Data!F33+Data!G33)/2)) -> 1.6520231 | J25: Asset turnover measures how efficiently the firm uses its assets to generate sales. It measures the number of sales dollars generated per average dollar invested in assets.
A26: = Return on Assets | B26: =IF(ISERROR((Data!C86+(1-Data!C142)*(-Data!C78))/((Data!B33+Data!C33)/2)),"",(Data!C86+(1-Data!C142)*(-Data!C78))/((Data!B33+Data!C33)/2)) -> 0.18472534 | C26: =IF(ISERROR((Data!D86+(1-Data!D142)*(-Data!D78))/((Data!C33+Data!D33)/2)),"",(Data!D86+(1-Data!D142)*(-Data!D78))/((Data!C33+Data!D33)/2)) -> 0.18048666 | D26: =IF(ISERROR((Data!E86+(1-Data!E142)*(-Data!E78))/((Data!D33+Data!E33)/2)),"",(Data!E86+(1-Data!E142)*(-Data!E78))/((Data!D33+Data!E33)/2)) -> 0.0027427176 | E26: =IF(ISERROR((Data!F86+(1-Data!F142)*(-Data!F78))/((Data!E33+Data!F33)/2)),"",(Data!F86+(1-Data!F142)*(-Data!F78))/((Data!E33+Data!F33)/2)) -> 0.18943897 | F26: =IF(ISERROR((Data!G86+(1-Data!G142)*(-Data!G78))/((Data!F33+Data!G33)/2)),"",(Data!G86+(1-Data!G142)*(-Data!G78))/((Data!F33+Data!G33)/2)) -> 0.24183081 | J26: Rate of return on assets is the product of the firm's profitability and its efficiency.
A28: RETURN ON ASSETS (excluding the effects of nonrecurring items): | J28: See the preceding FSAP User Guides on ROA.
A29: Profit Margin for ROA | B29: =IF(ISERROR((Data!C86+((1-Data!C142)*-Data!C78)-Data!C144)/Data!C65),"",(Data!C86+((1-Data!C142)*-Data!C78)-Data!C144)/Data!C65) -> 0.10683524 | C29: =IF(ISERROR((Data!D86+((1-Data!D142)*-Data!D78)-Data!D144)/Data!D65),"",(Data!D86+((1-Data!D142)*-Data!D78)-Data!D144)/Data!D65) -> 0.10571488 | D29: =IF(ISERROR((Data!E86+((1-Data!E142)*-Data!E78)-Data!E144)/Data!E65),"",(Data!E86+((1-Data!E142)*-Data!E78)-Data!E144)/Data!E65) -> 0.12354575 | E29: =IF(ISERROR((Data!F86+((1-Data!F142)*-Data!F78)-Data!F144)/Data!F65),"",(Data!F86+((1-Data!F142)*-Data!F78)-Data!F144)/Data!F65) -> 0.12744774 | F29: =IF(ISERROR((Data!G86+((1-Data!G142)*-Data!G78)-Data!G144)/Data!G65),"",(Data!G86+((1-Data!G142)*-Data!G78)-Data!G144)/Data!G65) -> 0.13520798 | J29: These computations of ROA exclude the after-tax effects of nonrecurring items in income to measure the firm's persistent ROA.
A30: x Asset Turnover | B30: =IF(ISERROR(Data!C65/((Data!B33+Data!C33)/2)),"",Data!C65/((Data!B33+Data!C33)/2)) -> 1.7023344 | C30: =IF(ISERROR(Data!D65/((Data!C33+Data!D33)/2)),"",Data!D65/((Data!C33+Data!D33)/2)) -> 1.7072967 | D30: =IF(ISERROR(Data!E65/((Data!D33+Data!E33)/2)),"",Data!E65/((Data!D33+Data!E33)/2)) -> 1.5065743 | E30: =IF(ISERROR(Data!F65/((Data!E33+Data!F33)/2)),"",Data!F65/((Data!E33+Data!F33)/2)) -> 1.4771527 | F30: =IF(ISERROR(Data!G65/((Data!F33+Data!G33)/2)),"",Data!G65/((Data!F33+Data!G33)/2)) -> 1.6520231
A31: = Return on Assets | B31: =IF(ISERROR((Data!C86+((1-Data!C142)*-Data!C78)-Data!C144)/((Data!B33+Data!C33)/2)),"",(Data!C86+((1-Data!C142)*-Data!C78)-Data!C144)/((Data!B33+Data!C33)/2)) -> 0.1818693 | C31: =IF(ISERROR((Data!D86+((1-Data!D142)*-Data!D78)-Data!D144)/((Data!C33+Data!D33)/2)),"",(Data!D86+((1-Data!D142)*-Data!D78)-Data!D144)/((Data!C33+Data!D33)/2)) -> 0.18048666 | D31: =IF(ISERROR((Data!E86+((1-Data!E142)*-Data!E78)-Data!E144)/((Data!D33+Data!E33)/2)),"",(Data!E86+((1-Data!E142)*-Data!E78)-Data!E144)/((Data!D33+Data!E33)/2)) -> 0.18613086 | E31: =IF(ISERROR((Data!F86+((1-Data!F142)*-Data!F78)-Data!F144)/((Data!E33+Data!F33)/2)),"",(Data!F86+((1-Data!F142)*-Data!F78)-Data!F144)/((Data!E33+Data!F33)/2)) -> 0.18825978 | F31: =IF(ISERROR((Data!G86+((1-Data!G142)*-Data!G78)-Data!G144)/((Data!F33+Data!G33)/2)),"",(Data!G86+((1-Data!G142)*-Data!G78)-Data!G144)/((Data!F33+Data!G33)/2)) -> 0.22336671
A33: RETURN ON COMMON EQUITY (based on reported amounts): | J33: Return on common equity measures the rate of return the firm earns per average dollar in common shareholders' equity.
A34: Profit Margin for ROCE | B34: =IF(ISERROR((Data!C88-Data!C146)/Data!C65),"",(Data!C88-Data!C146)/Data!C65) -> 0.10646645 | C34: =IF(ISERROR((Data!D88-Data!D146)/Data!D65),"",(Data!D88-Data!D146)/Data!D65) -> 0.10404902 | D34: =IF(ISERROR((Data!E88-Data!E146)/Data!E65),"",(Data!E88-Data!E146)/Data!E65) -> 0.00055829096 | E34: =IF(ISERROR((Data!F88-Data!F146)/Data!F65),"",(Data!F88-Data!F146)/Data!F65) -> 0.12573718 | F34: =IF(ISERROR((Data!G88-Data!G146)/Data!G65),"",(Data!G88-Data!G146)/Data!G65) -> 0.14389413 | J34: Profit margin for ROCE measures the net profit margin per dollar of sales. Profit margin for ROCE is measured after deducting any preferred dividends from net income, in order to compute the amount of net income available to common equity shareholders.
A35: x Asset Turnover | B35: =IF(ISERROR(Data!C65/((Data!B33+Data!C33)/2)),"",Data!C65/((Data!B33+Data!C33)/2)) -> 1.7023344 | C35: =IF(ISERROR(Data!D65/((Data!C33+Data!D33)/2)),"",Data!D65/((Data!C33+Data!D33)/2)) -> 1.7072967 | D35: =IF(ISERROR(Data!E65/((Data!D33+Data!E33)/2)),"",Data!E65/((Data!D33+Data!E33)/2)) -> 1.5065743 | E35: =IF(ISERROR(Data!F65/((Data!E33+Data!F33)/2)),"",Data!F65/((Data!E33+Data!F33)/2)) -> 1.4771527 | F35: =IF(ISERROR(Data!G65/((Data!F33+Data!G33)/2)),"",Data!G65/((Data!F33+Data!G33)/2)) -> 1.6520231 | J35: Asset turnover measures how efficiently the firm uses its assets to generate sales. It measures the number of sales dollars generated per average dollar invested in assets.
A36: x Capital Structure Leverage | B36: =IF(ISERROR(((Data!B33+Data!C33)/2)/((Data!B57+Data!C57)/2)),"",((Data!B33+Data!C33)/2)/((Data!B57+Data!C57)/2)) -> 1.7055809 | C36: =IF(ISERROR(((Data!C33+Data!D33)/2)/((Data!C57+Data!D57)/2)),"",((Data!C33+Data!D33)/2)/((Data!C57+Data!D57)/2)) -> 1.6410116 | D36: =IF(ISERROR(((Data!D33+Data!E33)/2)/((Data!D57+Data!E57)/2)),"",((Data!D33+Data!E33)/2)/((Data!D57+Data!E57)/2)) -> 2.0581383 | E36: =IF(ISERROR(((Data!E33+Data!F33)/2)/((Data!E57+Data!F57)/2)),"",((Data!E33+Data!F33)/2)/((Data!E57+Data!F57)/2)) -> 2.2835463 | F36: =IF(ISERROR(((Data!F33+Data!G33)/2)/((Data!F57+Data!G57)/2)),"",((Data!F33+Data!G33)/2)/((Data!F57+Data!G57)/2)) -> 2.0918909 | J36: Capital structure leverage measures the average amount invested in assets divided by the average amount financed by common equity shareholders.
A37: = Return on Common Equity | B37: =IF(ISERROR((Data!C88-Data!C146)/((Data!B57+Data!C57)/2)),"",(Data!C88-Data!C146)/((Data!B57+Data!C57)/2)) -> 0.30912204 | C37: =IF(ISERROR((Data!D88-Data!D146)/((Data!C57+Data!D57)/2)),"",(Data!D88-Data!D146)/((Data!C57+Data!D57)/2)) -> 0.2915135 | D37: =IF(ISERROR((Data!E88-Data!E146)/((Data!D57+Data!E57)/2)),"",(Data!E88-Data!E146)/((Data!D57+Data!E57)/2)) -> 0.0017311142 | E37: =IF(ISERROR((Data!F88-Data!F146)/((Data!E57+Data!F57)/2)),"",(Data!F88-Data!F146)/((Data!E57+Data!F57)/2)) -> 0.42412994 | F37: =IF(ISERROR((Data!G88-Data!G146)/((Data!F57+Data!G57)/2)),"",(Data!G88-Data!G146)/((Data!F57+Data!G57)/2)) -> 0.49727683 | J37: Rate of return on common equity is the product of the firm's profitability, efficiency, and leverage.
A39: RETURN ON COMMON EQUITY (excluding the effects of nonrecurring items): | J39: See the preceding FSAP User Guides on ROCE.
A40: Profit Margin for ROCE | B40: =IF(ISERROR((Data!C88-Data!C146-Data!C144)/Data!C65),"",(Data!C88-Data!C146-Data!C144)/Data!C65) -> 0.10478873 | C40: =IF(ISERROR((Data!D88-Data!D146-Data!D144)/Data!D65),"",(Data!D88-Data!D146-Data!D144)/Data!D65) -> 0.10404902 | D40: =IF(ISERROR((Data!E88-Data!E146-Data!E144)/Data!E65),"",(Data!E88-Data!E146-Data!E144)/Data!E65) -> 0.12228354 | E40: =IF(ISERROR((Data!F88-Data!F146-Data!F144)/Data!F65),"",(Data!F88-Data!F146-Data!F144)/Data!F65) -> 0.1249389 | F40: =IF(ISERROR((Data!G88-Data!G146-Data!G144)/Data!G65),"",(Data!G88-Data!G146-Data!G144)/Data!G65) -> 0.13271747 | J40: These computations of ROCE exclude the after-tax effects of nonrecurring items in income to measure the firm's persistent ROCE.
A41: x Asset Turnover | B41: =IF(ISERROR(Data!C65/((Data!B33+Data!C33)/2)),"",Data!C65/((Data!B33+Data!C33)/2)) -> 1.7023344 | C41: =IF(ISERROR(Data!D65/((Data!C33+Data!D33)/2)),"",Data!D65/((Data!C33+Data!D33)/2)) -> 1.7072967 | D41: =IF(ISERROR(Data!E65/((Data!D33+Data!E33)/2)),"",Data!E65/((Data!D33+Data!E33)/2)) -> 1.5065743 | E41: =IF(ISERROR(Data!F65/((Data!E33+Data!F33)/2)),"",Data!F65/((Data!E33+Data!F33)/2)) -> 1.4771527 | F41: =IF(ISERROR(Data!G65/((Data!F33+Data!G33)/2)),"",Data!G65/((Data!F33+Data!G33)/2)) -> 1.6520231
A42: x Capital Structure Leverage | B42: =IF(ISERROR(((Data!B33+Data!C33)/2)/((Data!B57+Data!C57)/2)),"",((Data!B33+Data!C33)/2)/((Data!B57+Data!C57)/2)) -> 1.7055809 | C42: =IF(ISERROR(((Data!C33+Data!D33)/2)/((Data!C57+Data!D57)/2)),"",((Data!C33+Data!D33)/2)/((Data!C57+Data!D57)/2)) -> 1.6410116 | D42: =IF(ISERROR(((Data!D33+Data!E33)/2)/((Data!D57+Data!E57)/2)),"",((Data!D33+Data!E33)/2)/((Data!D57+Data!E57)/2)) -> 2.0581383 | E42: =IF(ISERROR(((Data!E33+Data!F33)/2)/((Data!E57+Data!F57)/2)),"",((Data!E33+Data!F33)/2)/((Data!E57+Data!F57)/2)) -> 2.2835463 | F42: =IF(ISERROR(((Data!F33+Data!G33)/2)/((Data!F57+Data!G57)/2)),"",((Data!F33+Data!G33)/2)/((Data!F57+Data!G57)/2)) -> 2.0918909
A43: = Return on Common Equity | B43: =IF(ISERROR((Data!C88-Data!C146-Data!C144)/((Data!B57+Data!C57)/2)),"",(Data!C88-Data!C146-Data!C144)/((Data!B57+Data!C57)/2)) -> 0.30425083 | C43: =IF(ISERROR((Data!D88-Data!D146-Data!D144)/((Data!C57+Data!D57)/2)),"",(Data!D88-Data!D146-Data!D144)/((Data!C57+Data!D57)/2)) -> 0.2915135 | D43: =IF(ISERROR((Data!E88-Data!E146-Data!E144)/((Data!D57+Data!E57)/2)),"",(Data!E88-Data!E146-Data!E144)/((Data!D57+Data!E57)/2)) -> 0.37916927 | E43: =IF(ISERROR((Data!F88-Data!F146-Data!F144)/((Data!E57+Data!F57)/2)),"",(Data!F88-Data!F146-Data!F144)/((Data!E57+Data!F57)/2)) -> 0.42143721 | F43: =IF(ISERROR((Data!G88-Data!G146-Data!G144)/((Data!F57+Data!G57)/2)),"",(Data!G88-Data!G146-Data!G144)/((Data!F57+Data!G57)/2)) -> 0.45865194
A45: OPERATING PERFORMANCE:
A46: Gross Profit / Revenues | B46: =IF(ISERROR(Data!C67/Data!C65),"",Data!C67/Data!C65) -> 0.57699737 | C46: =IF(ISERROR(Data!D67/Data!D65),"",Data!D67/Data!D65) -> 0.56289334 | D46: =IF(ISERROR(Data!E67/Data!E65),"",Data!E67/Data!E65) -> 0.57070116 | E46: =IF(ISERROR(Data!F67/Data!F65),"",Data!F67/Data!F65) -> 0.5829959 | F46: =IF(ISERROR(Data!G67/Data!G65),"",Data!G67/Data!G65) -> 0.59361155 | J46: Gross profit margin as a percent of revenues.
A47: Operating Profit / Revenues | B47: =IF(ISERROR(Data!C76/Data!C65),"",Data!C76/Data!C65) -> 0.14772999 | C47: =IF(ISERROR(Data!D76/Data!D65),"",Data!D76/Data!D65) -> 0.1501861 | D47: =IF(ISERROR(Data!E76/Data!E65),"",Data!E76/Data!E65) -> -0.021887696 | E47: =IF(ISERROR(Data!F76/Data!F65),"",Data!F76/Data!F65) -> 0.18732596 | F47: =IF(ISERROR(Data!G76/Data!G65),"",Data!G76/Data!G65) -> 0.18791715 | J47: Operating income as a percent of revenues.
A48: Net Income / Revenues | B48: =IF(ISERROR(Data!C88/Data!C65),"",Data!C88/Data!C65) -> 0.10646645 | C48: =IF(ISERROR(Data!D88/Data!D65),"",Data!D88/Data!D65) -> 0.10404902 | D48: =IF(ISERROR(Data!E88/Data!E65),"",Data!E88/Data!E65) -> 0.00055829096 | E48: =IF(ISERROR(Data!F88/Data!F65),"",Data!F88/Data!F65) -> 0.12573718 | F48: =IF(ISERROR(Data!G88/Data!G65),"",Data!G88/Data!G65) -> 0.14389413 | J48: Net income as a percent of revenues.
A49: Comprehensive Income / Revenues | B49: =IF(ISERROR(Data!C92/Data!C65),"",Data!C92/Data!C65) -> 0.10573143 | C49: =IF(ISERROR(Data!D92/Data!D65),"",Data!D92/Data!D65) -> 0.10234219 | D49: =IF(ISERROR(Data!E92/Data!E65),"",Data!E92/Data!E65) -> 0.0035380849 | E49: =IF(ISERROR(Data!F92/Data!F65),"",Data!F92/Data!F65) -> 0.12320189 | F49: =IF(ISERROR(Data!G92/Data!G65),"",Data!G92/Data!G65) -> 0.13379117 | J49: Comprehensive income as a percent of revenues.
A51: PERSISTENT OPERATING PERFORMANCE (excluding the effects of nonrecurring items):
A52: Persistent Operating Profit / Revenues | B52: =IF(ISERROR((Data!C76-Data!C75)/Data!C65),"",(Data!C76-Data!C75)/Data!C65) -> 0.14514888 | C52: =IF(ISERROR((Data!D76-Data!D75)/Data!D65),"",(Data!D76-Data!D75)/Data!D65) -> 0.1501861 | D52: =IF(ISERROR((Data!E76-Data!E75)/Data!E65),"",(Data!E76-Data!E75)/Data!E65) -> 0.16538192 | E52: =IF(ISERROR((Data!F76-Data!F75)/Data!F65),"",(Data!F76-Data!F75)/Data!F65) -> 0.18609784 | F52: =IF(ISERROR((Data!G76-Data!G75)/Data!G65),"",(Data!G76-Data!G75)/Data!G65) -> 0.18791715 | J52: Operating income as a percent of revenues after excluding the effects of non-recurring operating income items (such as non-recurring operating expenses and losses).
A53: Persistent Net Income / Revenues | B53: =IF(ISERROR((Data!C88-Data!C144)/Data!C65),"",(Data!C88-Data!C144)/Data!C65) -> 0.10478873 | C53: =IF(ISERROR((Data!D88-Data!D144)/Data!D65),"",(Data!D88-Data!D144)/Data!D65) -> 0.10404902 | D53: =IF(ISERROR((Data!E88-Data!E144)/Data!E65),"",(Data!E88-Data!E144)/Data!E65) -> 0.12228354 | E53: =IF(ISERROR((Data!F88-Data!F144)/Data!F65),"",(Data!F88-Data!F144)/Data!F65) -> 0.1249389 | F53: =IF(ISERROR((Data!G88-Data!G144)/Data!G65),"",(Data!G88-Data!G144)/Data!G65) -> 0.13271747 | J53: Net income as a percent of revenues, after excluding the effects of non-recurring items in income.
A55: GROWTH RATES:
A56: Revenue Growth | B56: =IF(ISERROR(Data!C65/Data!B65-1),"",Data!C65/Data!B65-1) -> 0.092739601 | C56: =IF(ISERROR(Data!D65/Data!C65-1),"",Data!D65/Data!C65-1) -> 0.13667054 | D56: =IF(ISERROR(Data!E65/Data!D65-1),"",Data!E65/Data!D65-1) -> 0.11784654 | E56: =IF(ISERROR(Data!F65/Data!E65-1),"",Data!F65/Data!E65-1) -> 0.10634434 | F56: =IF(ISERROR(Data!G65/Data!F65-1),"",Data!G65/Data!F65-1) -> 0.16506159 | J56: Year-on-year growth rate in revenues.
A57: Net Income Growth | B57: =IF(ISERROR(Data!C88/Data!B88-1),"",Data!C88/Data!B88-1) -> 0.31736464 | C57: =IF(ISERROR(Data!D88/Data!C88-1),"",Data!D88/Data!C88-1) -> 0.11086136 | D57: =IF(ISERROR(Data!E88/Data!D88-1),"",Data!E88/Data!D88-1) -> -0.99400202 | E57: =IF(ISERROR(Data!F88/Data!E88-1),"",Data!F88/Data!E88-1) -> 248.16867 | F57: =IF(ISERROR(Data!G88/Data!F88-1),"",Data!G88/Data!F88-1) -> 0.3333011 | J57: Year-on-year growth rate in net income.
A58: Persistent Net Income Growth | B58: =IF(ISERROR(((Data!C88-Data!C144)/(Data!B88-Data!B144))-1),"",((Data!C88-Data!C144)/(Data!B88-Data!B144))-1) -> 0.25102801 | C58: =IF(ISERROR(((Data!D88-Data!D144)/(Data!C88-Data!C144))-1),"",((Data!D88-Data!D144)/(Data!C88-Data!C144))-1) -> 0.12864681 | D58: =IF(ISERROR(((Data!E88-Data!E144)/(Data!D88-Data!D144))-1),"",((Data!E88-Data!E144)/(Data!D88-Data!D144))-1) -> 0.31374837 | E58: =IF(ISERROR(((Data!F88-Data!F144)/(Data!E88-Data!E144))-1),"",((Data!F88-Data!F144)/(Data!E88-Data!E144))-1) -> 0.1303683 | F58: =IF(ISERROR(((Data!G88-Data!G144)/(Data!F88-Data!F144))-1),"",((Data!G88-Data!G144)/(Data!F88-Data!F144))-1) -> 0.23759714 | J58: Year-on-year growth rate in net income, after excluding the effects of non-recurring items in income.
A60: OPERATING CONTROL:
A61: Gross Profit Control Index | B61: =IF(ISERROR((Data!C67/Data!B67)/(Data!C65/Data!B65)),"",(Data!C67/Data!B67)/(Data!C65/Data!B65)) -> 0.98869249 | C61: =IF(ISERROR((Data!D67/Data!C67)/(Data!D65/Data!C65)),"",(Data!D67/Data!C67)/(Data!D65/Data!C65)) -> 0.97555617 | D61: =IF(ISERROR((Data!E67/Data!D67)/(Data!E65/Data!D65)),"",(Data!E67/Data!D67)/(Data!E65/Data!D65)) -> 1.0138709 | E61: =IF(ISERROR((Data!F67/Data!E67)/(Data!F65/Data!E65)),"",(Data!F67/Data!E67)/(Data!F65/Data!E65)) -> 1.0215432 | F61: =IF(ISERROR((Data!G67/Data!F67)/(Data!G65/Data!F65)),"",(Data!G67/Data!F67)/(Data!G65/Data!F65)) -> 1.0182088 | J61: The rate of change in gross profit relative to the rate of change in revenues.
A62: Operating Profit Contol Index | B62: =IF(ISERROR((Data!C76/Data!B76)/(Data!C65/Data!B65)),"",(Data!C76/Data!B76)/(Data!C65/Data!B65)) -> 1.1144174 | C62: =IF(ISERROR((Data!D76/Data!C76)/(Data!D65/Data!C65)),"",(Data!D76/Data!C76)/(Data!D65/Data!C65)) -> 1.0166256 | D62: =IF(ISERROR((Data!E76/Data!D76)/(Data!E65/Data!D65)),"",(Data!E76/Data!D76)/(Data!E65/Data!D65)) -> -0.14573717 | E62: =IF(ISERROR((Data!F76/Data!E76)/(Data!F65/Data!E65)),"",(Data!F76/Data!E76)/(Data!F65/Data!E65)) -> -8.5585054 | F62: =IF(ISERROR((Data!G76/Data!F76)/(Data!G65/Data!F65)),"",(Data!G76/Data!F76)/(Data!G65/Data!F65)) -> 1.0031559 | J62: The rate of change in operating income relative to the rate of change in revenues.
A63: Net Profit Contol Index | B63: =IF(ISERROR((Data!C86/Data!B86)/(Data!C65/Data!B65)),"",(Data!C86/Data!B86)/(Data!C65/Data!B65)) -> 1.2043484 | C63: =IF(ISERROR((Data!D86/Data!C86)/(Data!D65/Data!C65)),"",(Data!D86/Data!C86)/(Data!D65/Data!C65)) -> 0.9761274 | D63: =IF(ISERROR((Data!E86/Data!D86)/(Data!E65/Data!D65)),"",(Data!E86/Data!D86)/(Data!E65/Data!D65)) -> 0.0056851875 | E63: =IF(ISERROR((Data!F86/Data!E86)/(Data!F65/Data!E65)),"",(Data!F86/Data!E86)/(Data!F65/Data!E65)) -> 212.38045 | F63: =IF(ISERROR((Data!G86/Data!F86)/(Data!G65/Data!F65)),"",(Data!G86/Data!F86)/(Data!G65/Data!F65)) -> 1.1454141 | J63: The rate of change in net income relative to the rate of change in revenues.
A65: Profit Margin Decomposition:
A66: Gross Profit Margin | B66: =IF(ISERROR(Data!C67/Data!C65),"",Data!C67/Data!C65) -> 0.57699737 | C66: =IF(ISERROR(Data!D67/Data!D65),"",Data!D67/Data!D65) -> 0.56289334 | D66: =IF(ISERROR(Data!E67/Data!E65),"",Data!E67/Data!E65) -> 0.57070116 | E66: =IF(ISERROR(Data!F67/Data!F65),"",Data!F67/Data!F65) -> 0.5829959 | F66: =IF(ISERROR(Data!G67/Data!G65),"",Data!G67/Data!G65) -> 0.59361155 | J66: Gross profit margin as a percent of revenues.
A67: Operating Profit Index | B67: =IF(ISERROR(Data!C76/Data!C67),"",Data!C76/Data!C67) -> 0.25603235 | C67: =IF(ISERROR(Data!D76/Data!D67),"",Data!D76/Data!D67) -> 0.26681093 | D67: =IF(ISERROR(Data!E76/Data!E67),"",Data!E76/Data!E67) -> -0.038352289 | E67: =IF(ISERROR(Data!F76/Data!F67),"",Data!F76/Data!F67) -> 0.32131609 | F67: =IF(ISERROR(Data!G76/Data!G67),"",Data!G76/Data!G67) -> 0.31656586 | J67: Operating profit as a percent of gross profit. The complement of this percentage is the percent of gross profit absorbed by overhead and operating expenses.
A68: Leverage Index | B68: =IF(ISERROR(Data!C81/Data!C76),"",Data!C81/Data!C76) -> 1.0477871 | C68: =IF(ISERROR(Data!D81/Data!D76),"",Data!D81/Data!D76) -> 1.0308902 | D68: =IF(ISERROR(Data!E81/Data!E76),"",Data!E81/Data!E76) -> 0.70651506 | E68: =IF(ISERROR(Data!F81/Data!F76),"",Data!F81/Data!F76) -> 1.0255104 | F68: =IF(ISERROR(Data!G81/Data!G76),"",Data!G81/Data!G76) -> 1.0838656 | J68: Income before tax as a percent of operating profit. The complement of this percentage is the percent of operating profit absorbed by (net) financing costs. If this index is great than 100%, it implies financing income (interest income, income from equity affiliates) exceeds financing costs (interest expense).
A69: Tax Index | B69: =IF(ISERROR(Data!C86/Data!C81),"",Data!C86/Data!C81) -> 0.68908398 | C69: =IF(ISERROR(Data!D86/Data!D81),"",Data!D86/Data!D81) -> 0.67247827 | D69: =IF(ISERROR(Data!E86/Data!E81),"",Data!E86/Data!E81) -> -0.038277512 | E69: =IF(ISERROR(Data!F86/Data!F81),"",Data!F86/Data!F81) -> 0.65439757 | F69: =IF(ISERROR(Data!G86/Data!G81),"",Data!G86/Data!G81) -> 0.706969 | J69: Net income as a percent of income before tax. The complement of this percentage is the average effective tax rate. This index is also affected by items such as extraordinary gains and losses, discontinued operations, and changes in accounting principles.
A70: Net Profit Margin | B70: =IF(ISERROR(Data!C86/Data!C65),"",Data!C86/Data!C65) -> 0.10666302 | C70: =IF(ISERROR(Data!D86/Data!D65),"",Data!D86/Data!D65) -> 0.1041167 | D70: =IF(ISERROR(Data!E86/Data!E65),"",Data!E86/Data!E65) -> 0.00059192294 | E70: =IF(ISERROR(Data!F86/Data!F65),"",Data!F86/Data!F65) -> 0.12571286 | F70: =IF(ISERROR(Data!G86/Data!G65),"",Data!G86/Data!G65) -> 0.14399328 | J70: Net income as a percent of revenues. The net profit margin will also equal the product of the gross profit margin times the operating profit index, the leverage index and the tax index.
A72: Comprehensive Income Performance:
A73: Comprehensive Income Index | B73: =IF(ISERROR(Data!C92/Data!C86),"",Data!C92/Data!C86) -> 0.99126603 | C73: =IF(ISERROR(Data!D92/Data!D86),"",Data!D92/Data!D86) -> 0.9829566 | D73: =IF(ISERROR(Data!E92/Data!E86),"",Data!E92/Data!E86) -> 5.9772727 | E73: =IF(ISERROR(Data!F92/Data!F86),"",Data!F92/Data!F86) -> 0.98002612 | F73: =IF(ISERROR(Data!G92/Data!G86),"",Data!G92/Data!G86) -> 0.9291487 | J73: Comprehensive income as a percent of net income.
A74: Comprehensive Income Margin | B74: =IF(ISERROR(Data!C92/Data!C65),"",Data!C92/Data!C65) -> 0.10573143 | C74: =IF(ISERROR(Data!D92/Data!D65),"",Data!D92/Data!D65) -> 0.10234219 | D74: =IF(ISERROR(Data!E92/Data!E65),"",Data!E92/Data!E65) -> 0.0035380849 | E74: =IF(ISERROR(Data!F92/Data!F65),"",Data!F92/Data!F65) -> 0.12320189 | F74: =IF(ISERROR(Data!G92/Data!G65),"",Data!G92/Data!G65) -> 0.13379117 | J74: Comprehensive income as a percent of revenues.
A77: RISK FACTORS: | J77: Risk Factors:
A78: Year | B78: =Data!$C$11 -> 2011 | C78: =Data!$D$11 -> 2012 | D78: =Data!$E$11 -> 2013 | E78: =Data!$F$11 -> 2014 | F78: =Data!$G$11 -> 2015
A80: LIQUIDITY:
A81: Current Ratio | B81: =IF(ISERROR(Data!C24/Data!C44),"",Data!C24/Data!C44) -> 1.8281626 | C81: =IF(ISERROR(Data!D24/Data!D44),"",Data!D24/Data!D44) -> 1.9004435 | D81: =IF(ISERROR(Data!E24/Data!E44),"",Data!E24/Data!E44) -> 1.0174995 | E81: =IF(ISERROR(Data!F24/Data!F44),"",Data!F24/Data!F44) -> 1.3718695 | F81: =IF(ISERROR(Data!G24/Data!G44),"",Data!G24/Data!G44) -> 1.1913973 | J81: Current assets divided by current liabilities.
A82: Quick Ratio | B82: =IF(ISERROR((Data!C16+Data!C17+Data!C18)/Data!C44),"",(Data!C16+Data!C17+Data!C18)/Data!C44) -> 1.1741016 | C82: =IF(ISERROR((Data!D16+Data!D17+Data!D18)/Data!D44),"",(Data!D16+Data!D17+Data!D18)/Data!D44) -> 1.141687 | D82: =IF(ISERROR((Data!E16+Data!E17+Data!E18)/Data!E44),"",(Data!E16+Data!E17+Data!E18)/Data!E44) -> 0.70578171 | E82: =IF(ISERROR((Data!F16+Data!F17+Data!F18)/Data!F44),"",(Data!F16+Data!F17+Data!F18)/Data!F44) -> 0.81442722 | F82: =IF(ISERROR((Data!G16+Data!G17+Data!G18)/Data!G44),"",(Data!G16+Data!G17+Data!G18)/Data!G44) -> 0.63785411 | J82: More liquid current assets (cash and cash equivalents, marketable securities, accounts receivable) divided by current liabilities.
A83: Operating Cash Flow to Current Liabilities | B83: =IF(ISERROR(Data!C113/((Data!B44+Data!C44)/2)),"",Data!C113/((Data!B44+Data!C44)/2)) -> 0.8365457 | C83: =IF(ISERROR(Data!D113/((Data!C44+Data!D44)/2)),"",Data!D113/((Data!C44+Data!D44)/2)) -> 0.81682845 | D83: =IF(ISERROR(Data!E113/((Data!D44+Data!E44)/2)),"",Data!E113/((Data!D44+Data!E44)/2)) -> 0.76664338 | E83: =IF(ISERROR(Data!F113/((Data!E44+Data!F44)/2)),"",Data!F113/((Data!E44+Data!F44)/2)) -> 0.14443916 | F83: =IF(ISERROR(Data!G113/((Data!F44+Data!G44)/2)),"",Data!G113/((Data!F44+Data!G44)/2)) -> 1.1204387 | J83: Operating cash flows divided by the average amount of current liabilities.
A85: ASSET TURNOVER:
A86: Cash Turnover | B86: =IF(ISERROR(Data!C65/((Data!B16+Data!C16)/2)),"",Data!C65/((Data!B16+Data!C16)/2)) -> 10.121016 | C86: =IF(ISERROR(Data!D65/((Data!C16+Data!D16)/2)),"",Data!D65/((Data!C16+Data!D16)/2)) -> 11.383147 | D86: =IF(ISERROR(Data!E65/((Data!D16+Data!E16)/2)),"",Data!E65/((Data!D16+Data!E16)/2)) -> 7.8988391 | E86: =IF(ISERROR(Data!F65/((Data!E16+Data!F16)/2)),"",Data!F65/((Data!E16+Data!F16)/2)) -> 7.6785322 | F86: =IF(ISERROR(Data!G65/((Data!F16+Data!G16)/2)),"",Data!G65/((Data!F16+Data!G16)/2)) -> 11.834306 | J86: Revenues divided by the average cash balance.
A87: Days Sales Held in Cash | B87: =IF(ISERROR(365/B86),"",365/B86) -> 36.063575 | C87: =IF(ISERROR(365/C86),"",365/C86) -> 32.064946 | D87: =IF(ISERROR(365/D86),"",365/D86) -> 46.209322 | E87: =IF(ISERROR(365/E86),"",365/E86) -> 47.535126 | F87: =IF(ISERROR(365/F86),"",365/F86) -> 30.842535 | J87: The number of days sales held in cash is measured as 365 divided by the cash turnover rate. It measures the average number of days of sales held in cash and cash equivalents.
A88: Accounts Receivable Turnover | B88: =IF(ISERROR(Data!C65/((Data!B18+Data!C18)/2)),"",Data!C65/((Data!B18+Data!C18)/2)) -> 33.953569 | C88: =IF(ISERROR(Data!D65/((Data!C18+Data!D18)/2)),"",Data!D65/((Data!C18+Data!D18)/2)) -> 30.489454 | D88: =IF(ISERROR(Data!E65/((Data!D18+Data!E18)/2)),"",Data!E65/((Data!D18+Data!E18)/2)) -> 28.390719 | E88: =IF(ISERROR(Data!F65/((Data!E18+Data!F18)/2)),"",Data!F65/((Data!E18+Data!F18)/2)) -> 27.587722 | F88: =IF(ISERROR(Data!G65/((Data!F18+Data!G18)/2)),"",Data!G65/((Data!F18+Data!G18)/2)) -> 28.389185 | J88: Total revenues divided by the average balance in accounts receivable.
A89: Days Receivables Held | B89: =IF(ISERROR(365/B88),"",365/B88) -> 10.749974 | C89: =IF(ISERROR(365/C88),"",365/C88) -> 11.971352 | D89: =IF(ISERROR(365/D88),"",365/D88) -> 12.856314 | E89: =IF(ISERROR(365/E88),"",365/E88) -> 13.230523 | F89: =IF(ISERROR(365/F88),"",365/F88) -> 12.857009 | J89: The number of days in receivables is measured as 365 divided by the accounts receivable turnover rate. This measures the average number of days to collect receivables.
A90: Inventory Turnover | B90: =IF(ISERROR(-Data!C66/((Data!B19+Data!C19)/2)),"",-Data!C66/((Data!B19+Data!C19)/2)) -> 6.5592737 | C90: =IF(ISERROR(-Data!D66/((Data!C19+Data!D19)/2)),"",-Data!D66/((Data!C19+Data!D19)/2)) -> 5.2673402 | D90: =IF(ISERROR(-Data!E66/((Data!D19+Data!E19)/2)),"",-Data!E66/((Data!D19+Data!E19)/2)) -> 5.4255111 | E90: =IF(ISERROR(-Data!F66/((Data!E19+Data!F19)/2)),"",-Data!F66/((Data!E19+Data!F19)/2)) -> 6.2293266 | F90: =IF(ISERROR(-Data!G66/((Data!F19+Data!G19)/2)),"",-Data!G66/((Data!F19+Data!G19)/2)) -> 6.4968923 | J90: Cost of goods sold divided by the average amaount of inventory.
A91: Days Inventory Held | B91: =IF(ISERROR(365/B90),"",365/B90) -> 55.646405 | C91: =IF(ISERROR(365/C90),"",365/C90) -> 69.294936 | D91: =IF(ISERROR(365/D90),"",365/D90) -> 67.274768 | E91: =IF(ISERROR(365/E90),"",365/E90) -> 58.593814 | F91: =IF(ISERROR(365/F90),"",365/F90) -> 56.180706 | J91: The number of days in inventory is measured as 365 divided by the inventory turnover rate. This measures the average number of days to make and sell inventory.
A92: Accounts Payable Turnover | B92: =IF(ISERROR((-Data!C66+Data!C19-Data!B19)/((Data!C36+Data!B36)/2)),"",(-Data!C66+Data!C19-Data!B19)/((Data!C36+Data!B36)/2)) -> 13.06054 | C92: =IF(ISERROR((-Data!D66+Data!D19-Data!C19)/((Data!D36+Data!C36)/2)),"",(-Data!D66+Data!D19-Data!C19)/((Data!D36+Data!C36)/2)) -> 12.981558 | D92: =IF(ISERROR((-Data!E66+Data!E19-Data!D19)/((Data!E36+Data!D36)/2)),"",(-Data!E66+Data!E19-Data!D19)/((Data!E36+Data!D36)/2)) -> 14.052596 | E92: =IF(ISERROR((-Data!F66+Data!F19-Data!E19)/((Data!F36+Data!E36)/2)),"",(-Data!F66+Data!F19-Data!E19)/((Data!F36+Data!E36)/2)) -> 13.338209 | F92: =IF(ISERROR((-Data!G66+Data!G19-Data!F19)/((Data!G36+Data!F36)/2)),"",(-Data!G66+Data!G19-Data!F19)/((Data!G36+Data!F36)/2)) -> 13.142294 | J92: Inventory purchases (computed as cost of goods sold plus the change in inventory) divided by the average amount in accounts payable.
A93: Days Payables Held | B93: =IF(ISERROR(365/B92),"",365/B92) -> 27.946778 | C93: =IF(ISERROR(365/C92),"",365/C92) -> 28.116809 | D93: =IF(ISERROR(365/D92),"",365/D92) -> 25.973848 | E93: =IF(ISERROR(365/E92),"",365/E92) -> 27.364992 | F93: =IF(ISERROR(365/F92),"",365/F92) -> 27.772929 | J93: The number of days in payables is measured as 365 divided by the accounts payable turnover rate. This measures the average number of days to pay payables.
A94: Net Working Capital Days | B94: =IF(ISERROR(B89+B91-B93),"",B89+B91-B93) -> 38.449601 | C94: =IF(ISERROR(C89+C91-C93),"",C89+C91-C93) -> 53.149479 | D94: =IF(ISERROR(D89+D91-D93),"",D89+D91-D93) -> 54.157233 | E94: =IF(ISERROR(E89+E91-E93),"",E89+E91-E93) -> 44.459345 | F94: =IF(ISERROR(F89+F91-F93),"",F89+F91-F93) -> 41.264786 | J94: Net working capital days measures the number of days to make and sell inventory plus the number of days to collect receivables, minus the number of days to pay payables.
A95: Revenues / Average Net Fixed Assets | B95: =IF(ISERROR(Data!C65/((Data!B27+Data!B28+Data!C27+Data!C28)/2)),"",Data!C65/((Data!B27+Data!B28+Data!C27+Data!C28)/2)) -> 4.9042859 | C95: =IF(ISERROR(Data!D65/((Data!C27+Data!C28+Data!D27+Data!D28)/2)),"",Data!D65/((Data!C27+Data!C28+Data!D27+Data!D28)/2)) -> 5.305052 | D95: =IF(ISERROR(Data!E65/((Data!D27+Data!D28+Data!E27+Data!E28)/2)),"",Data!E65/((Data!D27+Data!D28+Data!E27+Data!E28)/2)) -> 5.0745127 | E95: =IF(ISERROR(Data!F65/((Data!E27+Data!E28+Data!F27+Data!F28)/2)),"",Data!F65/((Data!E27+Data!E28+Data!F27+Data!F28)/2)) -> 4.8955428 | F95: =IF(ISERROR(Data!G65/((Data!F27+Data!F28+Data!G27+Data!G28)/2)),"",Data!G65/((Data!F27+Data!F28+Data!G27+Data!G28)/2)) -> 5.0379767 | J95: Total revenues divided by the average balance in net property, plant, and equipment. This measures efficiency is using fixed assets to generate revenues.
A96: CAPEX Index | B96: =(Data!C115+Data!C114)/-Data!C145 -> 0.75666302 | C96: =(Data!D115+Data!D114)/-Data!D145 -> 1.4770005 | D96: =(Data!E115+Data!E114)/-Data!E145 -> 1.7768174 | E96: =(Data!F115+Data!F114)/-Data!F145 -> 1.56942 | F96: =(Data!G115+Data!G114)/-Data!G145 -> 1.4751075 | J96: Capital expenditures to acquire PPE divided by depreciation expense.
A97: Expected Useful Life of PPE for Depreciation | B97: =((Data!C27+Data!B27)/2)/Data!C145 -> 11.000183 | C97: =((Data!D27+Data!C27)/2)/Data!D145 -> 11.340219 | D97: =((Data!E27+Data!D27)/2)/Data!E145 -> 11.332922 | E97: =((Data!F27+Data!E27)/2)/Data!F145 -> 11.0607 | F97: =((Data!G27+Data!F27)/2)/Data!G145 -> 10.309403 | J97: Net PPE (gross PPE minus accumulated depreciation) by depreciation expense. Average expected remaining useful life (in years) of PPE, assuming straight-line depreciation.
A98: Expected Remaining Useful Life of PPE | B98: =(Data!C27+Data!C28)/Data!C145 -> 4.2990142 | C98: =(Data!D27+Data!D28)/Data!D145 -> 4.6153446 | D98: =(Data!E27+Data!E28)/Data!E145 -> 4.9398055 | E98: =(Data!F27+Data!F28)/Data!F145 -> 4.7573341 | F98: =(Data!G27+Data!G28)/Data!G145 -> 4.6258203 | J98: Average gross PPE (at cost) divided by depreciation expense. Average expected useful life (in years) of PPE, assuming straight-line depreciation.
A101: SOLVENCY:
A102: Total Liabilities / Total Assets | B102: =IF(ISERROR(Data!C50/Data!C33),"",Data!C50/Data!C33) -> 0.40393185 | C102: =IF(ISERROR(Data!D50/Data!D33),"",Data!D50/Data!D33) -> 0.37773749 | D102: =IF(ISERROR(Data!E50/Data!E33),"",Data!E50/Data!E33) -> 0.61079997 | E102: =IF(ISERROR(Data!F50/Data!F33),"",Data!F50/Data!F33) -> 0.50955556 | F102: =IF(ISERROR(Data!G50/Data!G33),"",Data!G50/Data!G33) -> 0.53239671 | J102: This ratio measures the percentage of total ssets financed by total liabilities.
A103: Total Liabilities / Total Equity | B103: =IF(ISERROR(Data!C50/Data!C59),"",Data!C50/Data!C59) -> 0.67766052 | C103: =IF(ISERROR(Data!D50/Data!D59),"",Data!D50/Data!D59) -> 0.60703881 | D103: =IF(ISERROR(Data!E50/Data!E59),"",Data!E50/Data!E59) -> 1.5693729 | E103: =IF(ISERROR(Data!F50/Data!F59),"",Data!F50/Data!F59) -> 1.0389669 | F103: =IF(ISERROR(Data!G50/Data!G59),"",Data!G50/Data!G59) -> 1.1385786 | J103: This debt/equity ratio measures total liabiliteis as a percent of common shareholders' equity.
A104: LT Debt / LT Capital | B104: =IF(ISERROR(Data!C45/(Data!C45+Data!C59)),"",Data!C45/(Data!C45+Data!C59)) -> 0.11130692 | C104: =IF(ISERROR(Data!D45/(Data!D45+Data!D59)),"",Data!D45/(Data!D45+Data!D59)) -> 0.097032185 | D104: =IF(ISERROR(Data!E45/(Data!E45+Data!E59)),"",Data!E45/(Data!E45+Data!E59)) -> 0.22474359 | E104: =IF(ISERROR(Data!F45/(Data!F45+Data!F59)),"",Data!F45/(Data!F45+Data!F59)) -> 0.27974597 | F104: =IF(ISERROR(Data!G45/(Data!G45+Data!G59)),"",Data!G45/(Data!G45+Data!G59)) -> 0.28742669 | J104: This ratio measures the percent of debt financing relative to total long term capital (long term debt plus commmon shareholders' equity).
A105: LT Debt / Total Equity | B105: =IF(ISERROR(Data!C45/Data!C59),"",Data!C45/Data!C59) -> 0.12524787 | C105: =IF(ISERROR(Data!D45/Data!D59),"",Data!D45/Data!D59) -> 0.10745918 | D105: =IF(ISERROR(Data!E45/Data!E59),"",Data!E45/Data!E59) -> 0.28989581 | E105: =IF(ISERROR(Data!F45/Data!F59),"",Data!F45/Data!F59) -> 0.38839904 | F105: =IF(ISERROR(Data!G45/Data!G59),"",Data!G45/Data!G59) -> 0.40336438 | J105: This ratio measures the percent of long term debt financing relative to commmon shareholders' equity.
A106: Operating Cash Flow to Total Liabilities | B106: =IF(ISERROR(Data!C113/((Data!C50+Data!B50)/2)),"",Data!C113/((Data!C50+Data!B50)/2)) -> 0.56807652 | C106: =IF(ISERROR(Data!D113/((Data!D50+Data!C50)/2)),"",Data!D113/((Data!D50+Data!C50)/2)) -> 0.57596499 | D106: =IF(ISERROR(Data!E113/((Data!E50+Data!D50)/2)),"",Data!E113/((Data!E50+Data!D50)/2)) -> 0.57368011 | E106: =IF(ISERROR(Data!F113/((Data!F50+Data!E50)/2)),"",Data!F113/((Data!F50+Data!E50)/2)) -> 0.097142309 | F106: =IF(ISERROR(Data!G113/((Data!G50+Data!F50)/2)),"",Data!G113/((Data!G50+Data!F50)/2)) -> 0.6194044 | J106: Operating cash flows divided by the average amount of total liabilities.
A107: Interest Coverage Ratio (reported amounts) | B107: =IF(ISERROR((Data!C81-Data!C78)/(-Data!C78)),"",(Data!C81-Data!C78)/(-Data!C78)) -> 55.387387 | C107: =IF(ISERROR((Data!D81-Data!D78)/(-Data!D78)),"",(Data!D81-Data!D78)/(-Data!D78)) -> 63.969419 | D107: =IF(ISERROR((Data!E81-Data!E78)/(-Data!E78)),"",(Data!E81-Data!E78)/(-Data!E78)) -> -7.1814947 | E107: =IF(ISERROR((Data!F81-Data!F78)/(-Data!F78)),"",(Data!F81-Data!F78)/(-Data!F78)) -> 50.293292 | F107: =IF(ISERROR((Data!G81-Data!G78)/(-Data!G78)),"",(Data!G81-Data!G78)/(-Data!G78)) -> 56.361702 | J107: Net income before interest expense, income taxes, and minority interest in income, divided by interest expense.
A108: Interest Coverage ratio (recurring amounts) | B108: =IF(ISERROR((Data!C81-Data!C78-Data!C75-Data!C80)/-Data!C78),"",(Data!C81-Data!C78-Data!C75-Data!C80)/-Data!C78) -> 54.48048 | C108: =IF(ISERROR((Data!D81-Data!D78-Data!D75-Data!D80)/-Data!D78),"",(Data!D81-Data!D78-Data!D75-Data!D80)/-Data!D78) -> 63.969419 | D108: =IF(ISERROR((Data!E81-Data!E78-Data!E75-Data!E80)/-Data!E78),"",(Data!E81-Data!E78-Data!E75-Data!E80)/-Data!E78) -> 91.896797 | E108: =IF(ISERROR((Data!F81-Data!F78-Data!F75-Data!F80)/-Data!F78),"",(Data!F81-Data!F78-Data!F75-Data!F80)/-Data!F78) -> 49.978159 | F108: =IF(ISERROR((Data!G81-Data!G78-Data!G75-Data!G80)/-Data!G78),"",(Data!G81-Data!G78-Data!G75-Data!G80)/-Data!G78) -> 51.687943 | J108: Net income before interest expense, income taxes, minority interest in income, and non-recurring items divided by interest expense.
A110: RISK FACTORS:
A111: Bankruptcy Predictors:
A112: Altman Z Score | B112: =IF(ISERROR(1.2*(Data!C24-Data!C44)/Data!C33+1.4*(Data!C54/Data!C33)+3.3*((Data!C81-Data!C78)/Data!C33)+0.6*((Data!C147*Data!C150)/Data!C50)+1*(Data!C65/Data!C33)),"",1.2*(Data!C24-Data!C44)/Data!C33+1.4*(Data!C54/Data!C33)+3.3*((Data!C81-Data!C78)/Data!C33)+0.6*((Data!C147*Data!C150)/Data!C50)+1*(Data!C65/Data!C33)) -> 8.9597626 | C112: =IF(ISERROR(1.2*(Data!D24-Data!D44)/Data!D33+1.4*(Data!D54/Data!D33)+3.3*((Data!D81-Data!D78)/Data!D33)+0.6*((Data!D147*Data!D150)/Data!D50)+1*(Data!D65/Data!D33)),"",1.2*(Data!D24-Data!D44)/Data!D33+1.4*(Data!D54/Data!D33)+3.3*((Data!D81-Data!D78)/Data!D33)+0.6*((Data!D147*Data!D150)/Data!D50)+1*(Data!D65/Data!D33)) -> 10.870035 | D112: =IF(ISERROR(1.2*(Data!E24-Data!E44)/Data!E33+1.4*(Data!E54/Data!E33)+3.3*((Data!E81-Data!E78)/Data!E33)+0.6*((Data!E147*Data!E150)/Data!E50)+1*(Data!E65/Data!E33)),"",1.2*(Data!E24-Data!E44)/Data!E33+1.4*(Data!E54/Data!E33)+3.3*((Data!E81-Data!E78)/Data!E33)+0.6*((Data!E147*Data!E150)/Data!E50)+1*(Data!E65/Data!E33)) -> 6.6307396 | E112: =IF(ISERROR(1.2*(Data!F24-Data!F44)/Data!F33+1.4*(Data!F54/Data!F33)+3.3*((Data!F81-Data!F78)/Data!F33)+0.6*((Data!F147*Data!F150)/Data!F50)+1*(Data!F65/Data!F33)),"",1.2*(Data!F24-Data!F44)/Data!F33+1.4*(Data!F54/Data!F33)+3.3*((Data!F81-Data!F78)/Data!F33)+0.6*((Data!F147*Data!F150)/Data!F50)+1*(Data!F65/Data!F33)) -> 9.5162774 | F112: =IF(ISERROR(1.2*(Data!G24-Data!G44)/Data!G33+1.4*(Data!G54/Data!G33)+3.3*((Data!G81-Data!G78)/Data!G33)+0.6*((Data!G147*Data!G150)/Data!G50)+1*(Data!G65/Data!G33)),"",1.2*(Data!G24-Data!G44)/Data!G33+1.4*(Data!G54/Data!G33)+3.3*((Data!G81-Data!G78)/Data!G33)+0.6*((Data!G147*Data!G150)/Data!G50)+1*(Data!G65/Data!G33)) -> 10.976138 | J112: The Altman Z-score is a multivariate predictor of bankruptcy.
A113: Bankruptcy Probability | B113: =IF(ISERROR(NORMSDIST(1-B112)),"",NORMSDIST(1-B112)) -> 8.6184868e-16 | C113: =IF(ISERROR(NORMSDIST(1-C112)),"",NORMSDIST(1-C112)) -> 2.8072567e-23 | D113: =IF(ISERROR(NORMSDIST(1-D112)),"",NORMSDIST(1-D112)) -> 8.9719259e-09 | E113: =IF(ISERROR(NORMSDIST(1-E112)),"",NORMSDIST(1-E112)) -> 8.2381924e-18 | F113: =IF(ISERROR(NORMSDIST(1-F112)),"",NORMSDIST(1-F112)) -> 9.6933011e-24 | J113: The probability of bankruptcy over the next two years as indicated by the Altman Z-score.
A114: Earnings Manipulation Predictors:
A115: Beneish Earnings Manipulation Score | B115: =IF(ISERROR(-4.84+0.92*((Data!C18/Data!C65)/(Data!B18/Data!B65))+0.528*((Data!B67/Data!B65)/(Data!C67/Data!C65))+0.404*(((Data!C31+Data!C32+Data!C30)/Data!C33)/((Data!B31+Data!B32+Data!B30)/Data!B33))+0.892*(Data!C65/Data!B65)+0.115*((Data!B98/(Data!B27+Data!B28+Data!B98))/(Data!C98/(Data!C27+Data!C28+Data!C98)))-0.172*((-Data!C68/Data!C65)/(-Data!B68/Data!B65))-0.327*(((Data!C44+Data!C45)/Data!C60)/((Data!B44+Data!B45)/Data!B60))+4.67*((Data!C81+Data!C82-Data!C113)/Data!C33)),"",-4.84+0.92*((Data!C18/Data!C65)/(Data!B18/Data!B65))+0.528*((Data!B67/Data!B65)/(Data!C67/Data!C65))+0.404*(((Data!C31+Data!C32+Data!C30)/Data!C33)/((Data!B31+Data!B32+Data!B30)/Data!B33))+0.892*(Data!C65/Data!B65)+0.115*((Data!B98/(Data!B27+Data!B28+Data!B98))/(Data!C98/(Data!C27+Data!C28+Data!C98)))-0.172*((-Data!C68/Data!C65)/(-Data!B68/Data!B65))-0.327*(((Data!C44+Data!C45)/Data!C60)/((Data!B44+Data!B45)/Data!B60))+4.67*((Data!C81+Data!C82-Data!C113)/Data!C33)) -> -2.4426779 | C115: =IF(ISERROR(-4.84+0.92*((Data!D18/Data!D65)/(Data!C18/Data!C65))+0.528*((Data!C67/Data!C65)/(Data!D67/Data!D65))+0.404*(((Data!D31+Data!D32+Data!D30)/Data!D33)/((Data!C31+Data!C32+Data!C30)/Data!C33))+0.892*(Data!D65/Data!C65)+0.115*((Data!C98/(Data!C27+Data!C28+Data!C98))/(Data!D98/(Data!D27+Data!D28+Data!D98)))-0.172*((-Data!D68/Data!D65)/(-Data!C68/Data!C65))-0.327*(((Data!D44+Data!D45)/Data!D60)/((Data!C44+Data!C45)/Data!C60))+4.67*((Data!D81+Data!D82-Data!D113)/Data!D33)),"",-4.84+0.92*((Data!D18/Data!D65)/(Data!C18/Data!C65))+0.528*((Data!C67/Data!C65)/(Data!D67/Data!D65))+0.404*(((Data!D31+Data!D32+Data!D30)/Data!D33)/((Data!C31+Data!C32+Data!C30)/Data!C33))+0.892*(Data!D65/Data!C65)+0.115*((Data!C98/(Data!C27+Data!C28+Data!C98))/(Data!D98/(Data!D27+Data!D28+Data!D98)))-0.172*((-Data!D68/Data!D65)/(-Data!C68/Data!C65))-0.327*(((Data!D44+Data!D45)/Data!D60)/((Data!C44+Data!C45)/Data!C60))+4.67*((Data!D81+Data!D82-Data!D113)/Data!D33)) -> -2.3904748 | D115: =IF(ISERROR(-4.84+0.92*((Data!E18/Data!E65)/(Data!D18/Data!D65))+0.528*((Data!D67/Data!D65)/(Data!E67/Data!E65))+0.404*(((Data!E31+Data!E32+Data!E30)/Data!E33)/((Data!D31+Data!D32+Data!D30)/Data!D33))+0.892*(Data!E65/Data!D65)+0.115*((Data!D98/(Data!D27+Data!D28+Data!D98))/(Data!E98/(Data!E27+Data!E28+Data!E98)))-0.172*((-Data!E68/Data!E65)/(-Data!D68/Data!D65))-0.327*(((Data!E44+Data!E45)/Data!E60)/((Data!D44+Data!D45)/Data!D60))+4.67*((Data!E81+Data!E82-Data!E113)/Data!E33)),"",-4.84+0.92*((Data!E18/Data!E65)/(Data!D18/Data!D65))+0.528*((Data!D67/Data!D65)/(Data!E67/Data!E65))+0.404*(((Data!E31+Data!E32+Data!E30)/Data!E33)/((Data!D31+Data!D32+Data!D30)/Data!D33))+0.892*(Data!E65/Data!D65)+0.115*((Data!D98/(Data!D27+Data!D28+Data!D98))/(Data!E98/(Data!E27+Data!E28+Data!E98)))-0.172*((-Data!E68/Data!E65)/(-Data!D68/Data!D65))-0.327*(((Data!E44+Data!E45)/Data!E60)/((Data!D44+Data!D45)/Data!D60))+4.67*((Data!E81+Data!E82-Data!E113)/Data!E33)) -> -3.6038738 | E115: =IF(ISERROR(-4.84+0.92*((Data!F18/Data!F65)/(Data!E18/Data!E65))+0.528*((Data!E67/Data!E65)/(Data!F67/Data!F65))+0.404*(((Data!F31+Data!F32+Data!F30)/Data!F33)/((Data!E31+Data!E32+Data!E30)/Data!E33))+0.892*(Data!F65/Data!E65)+0.115*((Data!E98/(Data!E27+Data!E28+Data!E98))/(Data!F98/(Data!F27+Data!F28+Data!F98)))-0.172*((-Data!F68/Data!F65)/(-Data!E68/Data!E65))-0.327*(((Data!F44+Data!F45)/Data!F60)/((Data!E44+Data!E45)/Data!E60))+4.67*((Data!F81+Data!F82-Data!F113)/Data!F33)),"",-4.84+0.92*((Data!F18/Data!F65)/(Data!E18/Data!E65))+0.528*((Data!E67/Data!E65)/(Data!F67/Data!F65))+0.404*(((Data!F31+Data!F32+Data!F30)/Data!F33)/((Data!E31+Data!E32+Data!E30)/Data!E33))+0.892*(Data!F65/Data!E65)+0.115*((Data!E98/(Data!E27+Data!E28+Data!E98))/(Data!F98/(Data!F27+Data!F28+Data!F98)))-0.172*((-Data!F68/Data!F65)/(-Data!E68/Data!E65))-0.327*(((Data!F44+Data!F45)/Data!F60)/((Data!E44+Data!E45)/Data!E60))+4.67*((Data!F81+Data!F82-Data!F113)/Data!F33)) -> -1.6566415 | F115: =IF(ISERROR(-4.84+0.92*((Data!G18/Data!G65)/(Data!F18/Data!F65))+0.528*((Data!F67/Data!F65)/(Data!G67/Data!G65))+0.404*(((Data!G31+Data!G32+Data!G30)/Data!G33)/((Data!F31+Data!F32+Data!F30)/Data!F33))+0.892*(Data!G65/Data!F65)+0.115*((Data!F98/(Data!F27+Data!F28+Data!F98))/(Data!G98/(Data!G27+Data!G28+Data!G98)))-0.172*((-Data!G68/Data!G65)/(-Data!F68/Data!F65))-0.327*(((Data!G44+Data!G45)/Data!G60)/((Data!F44+Data!F45)/Data!F60))+4.67*((Data!G81+Data!G82-Data!G113)/Data!G33)),"",-4.84+0.92*((Data!G18/Data!G65)/(Data!F18/Data!F65))+0.528*((Data!F67/Data!F65)/(Data!G67/Data!G65))+0.404*(((Data!G31+Data!G32+Data!G30)/Data!G33)/((Data!F31+Data!F32+Data!F30)/Data!F33))+0.892*(Data!G65/Data!F65)+0.115*((Data!F98/(Data!F27+Data!F28+Data!F98))/(Data!G98/(Data!G27+Data!G28+Data!G98)))-0.172*((-Data!G68/Data!G65)/(-Data!F68/Data!F65))-0.327*(((Data!G44+Data!G45)/Data!G60)/((Data!F44+Data!F45)/Data!F60))+4.67*((Data!G81+Data!G82-Data!G113)/Data!G33)) -> -2.4910019 | J115: The Beneish Earnings Manipulation Score is a multivariate indicator of the likelihood reported earnings numbers have been fraudulently manipulated.
A116: Earnings Manipulation Probability | B116: =IF(ISERROR(NORMSDIST(B115)),"",NORMSDIST(B115)) -> 0.0072893708 | C116: =IF(ISERROR(NORMSDIST(C115)),"",NORMSDIST(C115)) -> 0.0084133025 | D116: =IF(ISERROR(NORMSDIST(D115)),"",NORMSDIST(D115)) -> 0.00015675467 | E116: =IF(ISERROR(NORMSDIST(E115)),"",NORMSDIST(E115)) -> 0.048795993 | F116: =IF(ISERROR(NORMSDIST(F115)),"",NORMSDIST(F115)) -> 0.0063691727 | J116: The probability of earnings manipulation given the Beneish Earnings Manipulation Score.
A118: DIVIDEND and STOCK MARKET-BASED RATIOS:
A119: Stock Returns | B119: =IF(ISERROR((Data!C150+Data!C149)/Data!B150-1),"",(Data!C150+Data!C149)/Data!B150-1) -> 0.42944874 | C119: =IF(ISERROR((Data!D150+Data!D149)/Data!C150-1),"",(Data!D150+Data!D149)/Data!C150-1) -> 0.4042718 | D119: =IF(ISERROR((Data!E150+Data!E149)/Data!D150-1),"",(Data!E150+Data!E149)/Data!D150-1) -> 0.53310012 | E119: =IF(ISERROR((Data!F150+Data!F149)/Data!E150-1),"",(Data!F150+Data!F149)/Data!E150-1) -> 0.0059806691 | F119: =IF(ISERROR((Data!G150+Data!G149)/Data!F150-1),"",(Data!G150+Data!G149)/Data!F150-1) -> 0.52306594 | J119: Stock returns measure fiscal year-end share price plus dividends divided by beginning of year share price.
A120: Price-Earnings Ratio (reported amounts) | B120: =IF(ISERROR(Data!C150/Data!C148),"",Data!C150/Data!C148) -> 21.663674 | C120: =IF(ISERROR(Data!D150/Data!D148),"",Data!D150/Data!D148) -> 27.163904 | D120: =IF(ISERROR(Data!E150/Data!E148),"",Data!E150/Data!E148) -> 3802.5 | E120: =IF(ISERROR(Data!F150/Data!F148),"",Data!F150/Data!F148) -> 27.540146 | F120: =IF(ISERROR(Data!G150/Data!G148),"",Data!G150/Data!G148) -> 30.891304 | J120: Fiscal year-end share price divided by earnings per share.
A121: Price-Earnings Ratio (recurring amounts) | B121: =IF(ISERROR(Data!C150/(Data!C148-Data!C144/Data!C147)),"",Data!C150/(Data!C148-Data!C144/Data!C147)) -> 22.010559 | C121: =IF(ISERROR(Data!D150/(Data!D148-Data!D144/Data!D147)),"",Data!D150/(Data!D148-Data!D144/Data!D147)) -> 27.163904 | D121: =IF(ISERROR(Data!E150/(Data!E148-Data!E144/Data!E147)),"",Data!E150/(Data!E148-Data!E144/Data!E147)) -> 31.391434 | E121: =IF(ISERROR(Data!F150/(Data!F148-Data!F144/Data!F147)),"",Data!F150/(Data!F148-Data!F144/Data!F147)) -> 27.717358 | F121: =IF(ISERROR(Data!G150/(Data!G148-Data!G144/Data!G147)),"",Data!G150/(Data!G148-Data!G144/Data!G147)) -> 33.518417 | J121: Fiscal year-end share price divided by earnings per share after excluding the per-share effects of non-recurring items in income.
A122: Market Value to Book Value Ratio | B122: =IF(ISERROR((Data!C147*Data!C150)/Data!C57),"",(Data!C147*Data!C150)/Data!C57) -> 6.1537276 | C122: =IF(ISERROR((Data!D147*Data!D150)/Data!D57),"",(Data!D147*Data!D150)/Data!D57) -> 7.355137 | D122: =IF(ISERROR((Data!E147*Data!E150)/Data!E57),"",(Data!E147*Data!E150)/Data!E57) -> 12.785335 | E122: =IF(ISERROR((Data!F147*Data!F150)/Data!F57),"",(Data!F147*Data!F150)/Data!F57) -> 10.727858 | F122: =IF(ISERROR((Data!G147*Data!G150)/Data!G57),"",(Data!G147*Data!G150)/Data!G57) -> 14.508952 | J122: Market value of common equity divided by book value of common equity.
A123: Common Dividends per Share | B123: =Data!C149 -> 0.26126912 | C123: =Data!D149 -> 0.3423195 | D123: =Data!E149 -> 0.4174854 | E123: =Data!F149 -> 0.52241494 | F123: =Data!G149 -> 0.62527776
A124: Common Dividend Payout (% of Net Income) | B124: =Data!C129/Data!C88 -> -0.3126756 | C124: =Data!D129/Data!D88 -> -0.37071831 | D124: =Data!E129/Data!E88 -> -75.771084 | E124: =Data!F129/Data!F88 -> -0.37865674 | F124: =Data!G129/Data!G88 -> -0.33676652
A125: Common Dividend Yield (% of Share Price) | B125: =Data!C149/Data!C150 -> 0.014434758 | C125: =Data!D149/Data!D150 -> 0.013651824 | D125: =Data!E149/Data!E150 -> 0.010979235 | E125: =Data!F149/Data!F150 -> 0.013846142 | F125: =Data!G149/Data!G150 -> 0.011000664
...

Sheet Forecasts
A1: =Data!A1 -> Financial Statement Analysis Package (FSAP): Version 9.0
A2: =Data!A2 -> Financial Reporting, Financial Statement Analysis, and Valuation: A Strategic Perspective, 9th Edition | L2: FSAP User Guides:
A3: By James Wahlen, Steve Baginski, and Mark Bradshaw
L4: The FSAP user should only enter data in the blue-font cells shaded light green.
A6: The FSAP User Guides appear in column L to the right. | L6: A Comment on Entering Forecast Assumptions:
L7: This worksheet allows the FSAP user to build forecasts of future income statements, balance sheets, and statements of cash flows. FSAP automatically enters data from the DATA spreadsheet for the most recent three years in columns B, C, and D. This worksheet allows the user flexibility to compute forecast amounts for each income statement and balance sheet account. For each account, the user should enter the forecast computations in the first row (highlighted in green with bold blue font). In the second row for each account, the user can enter forecast assumption parameters (such as growth rates or percentages) to be used in the forecast computations. In the third row for each account, the user can enter a brief explanatory note to explain the forecast assumptions. The FSAP user can also develop more detailed computations of forecast amounts in the Forecast Development worksheet, and incorporate those forecast amounts by referencing them here in the Forecasts worksheet.
A9: FSAP OUTPUT: | B9: FINANCIAL STATEMENT FORECASTS
A10: =Data!A9 -> Analyst Name: | B10: =Data!B9 -> Wahlen, Baginski & Bradshaw
A11: =Data!A10 -> Company Name: | B11: =Data!B10 -> Starbucks
B13: Row Format: | E13: Row Format:
B14: Actual Amounts | E14: Forecast Amounts | J14: Year +6 and beyond: | L14: A Comment on Forecasts for Year +6 and Beyond:
B15: Common Size Percentage | E15: Forecast assumption | I15: Long-Run Growth Rate: | J15: =Valuation!$F$29 -> 0.03 | L15: For long-run forecast amounts, the FSAP user needs to enter a long-run growth rate assumption. FSAP will automatically use that growth rate to compute forecast amounts for all of the accounts for Year +6 and beyond. The FSAP user should not alter the specific forecast computations for any of the accounts for Year +6 and beyond. The FSAP user must be sure to enter the same long run growth rate assumption as a valuation parameter in the Valuation spreadsheet.
B16: Rate of Change Percentage | E16: Forecast assumption explanation | I16: Long-Run Growth Factor: | J16: =1+$J$15 -> 1.03
B18: Actuals | E18: Forecasts | L18: A Comment on Entering Forecast Assumptions:
A19: Year | B19: =Data!E11 -> 2013 | C19: =Data!F11 -> 2014 | D19: =Data!G11 -> 2015 | E19: Year +1 | F19: Year +2 | G19: Year +3 | H19: Year +4 | I19: Year +5 | J19: Year +6 | L19: This worksheet allows the FSAP user to build forecasts of future income statements, balance sheets, and statements of cash flows. FSAP automatically enters data from the DATA spreadsheet for the most recent three years in columns B, C, and D. This worksheet allows the user flexibility to compute forecast amounts for each income statement and balance sheet account. For each account, the user should enter the forecast computations in the first row (highlighted in green with bold blue font). In the second row for each account, the user can enter forecast assumption parameters (such as growth rates or percentages) to be used in the forecast computations. In the third row for each account, the user can enter a brief explanatory note to explain the forecast assumptions. The FSAP user can also develop more detailed computations of forecast amounts in the Forecast Development worksheet, and incorporate those forecast amounts by referencing them here in the Forecasts worksheet.
A20: INCOME STATEMENT
A21: =Data!A65 -> Revenues | B21: =Data!E65 -> 14866.8 | C21: =Data!F65 -> 16447.8 | D21: =Data!G65 -> 19162.7 | E21: ='Forecast Development'!E25 -> 21678.346 | F21: ='Forecast Development'!F25 -> 23670.508 | G21: ='Forecast Development'!G25 -> 26294.167 | H21: ='Forecast Development'!H25 -> 29159.361 | I21: ='Forecast Development'!I25 -> 32286.726 | J21: =I21*$J$16 -> 33255.328 | L21: Income Statement Default Assumptions:
A22: common size | B22: =B21/B$21 -> 1 | C22: =C21/C$21 -> 1 | D22: =D21/D$21 -> 1 | E22: =E21/D21-1 -> 0.13127829 | F22: =F21/E21-1 -> 0.091896381 | G22: =G21/F21-1 -> 0.11084083 | H22: =H21/G21-1 -> 0.10896692 | I22: =I21/H21-1 -> 0.1072508 | L22: The FSAP Forecasts worksheet defaults to assume that each income statement line item will remain the same percent of total revenues as in the most current year. The FSAP user must either accept this default as a reasonable expectation or override it and enter more reasonable forecast assumptions.
A23: rate of change | C23: =IF(ISERROR(C21/B21-1),"",C21/B21-1) -> 0.10634434 | D23: =IF(ISERROR(D21/C21-1),"",D21/C21-1) -> 0.16506159 | E23: See Forecast Development worksheet for details of revenues forecasts.
A24: =Data!A66 -> <Cost of sales and occupancy expense> | B24: =Data!E66 -> -6382.3 | C24: =Data!F66 -> -6858.8 | D24: =Data!G66 -> -7787.5 | E24: =-'Forecast Development'!E264 -> -8653.4939 | F24: =-'Forecast Development'!F264 -> -9390.3551 | G24: =-'Forecast Development'!G264 -> -10336.688 | H24: =-'Forecast Development'!H264 -> -11358.676 | I24: =-'Forecast Development'!I264 -> -12461.948 | J24: =I24*$J$16 -> -12835.807
A25: common size | B25: =B24/B$21 -> -0.42929884 | C25: =C24/C$21 -> -0.4170041 | D25: =D24/D$21 -> -0.40638845 | E25: =E24/E21 -> -0.39917684 | F25: =F24/F21 -> -0.39671117 | G25: =G24/G21 -> -0.39311716 | H25: =H24/H21 -> -0.38953789 | I25: =I24/I21 -> -0.38597745
A26: rate of change | C26: =IF(ISERROR(C24/B24-1),"",C24/B24-1) -> 0.074659605 | D26: =IF(ISERROR(D24/C24-1),"",D24/C24-1) -> 0.13540269 | E26: See Forecast Development worksheet.
A27: =Data!A67 -> Gross Profit | B27: =B21+B24 -> 8484.5 | C27: =C21+C24 -> 9589 | D27: =D21+D24 -> 11375.2 | E27: =E21+E24 -> 13024.853 | F27: =F21+F24 -> 14280.153 | G27: =G21+G24 -> 15957.479 | H27: =H21+H24 -> 17800.685 | I27: =I21+I24 -> 19824.778 | J27: =J21+J24 -> 20419.521
A28: common size | B28: =B27/B$21 -> 0.57070116 | C28: =C27/C$21 -> 0.5829959 | D28: =D27/D$21 -> 0.59361155 | E28: =E27/E$21 -> 0.60082316 | F28: =F27/F$21 -> 0.60328883 | G28: =G27/G$21 -> 0.60688284 | H28: =H27/H$21 -> 0.61046211 | I28: =I27/I$21 -> 0.61402255 | J28: =J27/J$21 -> 0.61402255
A29: rate of change | C29: =IF(ISERROR(C27/B27-1),"",C27/B27-1) -> 0.13017856 | D29: =IF(ISERROR(D27/C27-1),"",D27/C27-1) -> 0.18627594 | E29: =IF(ISERROR(E27/D27-1),"",E27/D27-1) -> 0.14502185 | F29: =IF(ISERROR(F27/E27-1),"",F27/E27-1) -> 0.096377325 | G29: =IF(ISERROR(G27/F27-1),"",G27/F27-1) -> 0.11745852 | H29: =IF(ISERROR(H27/G27-1),"",H27/G27-1) -> 0.11550737 | I29: =IF(ISERROR(I27/H27-1),"",I27/H27-1) -> 0.11370869
A31: =Data!A68 -> <Store Operating Expenses> | B31: =Data!E68 -> -4286.1 | C31: =Data!F68 -> -4638.2 | D31: =Data!G68 -> -5411.1 | E31: ='Forecast Development'!E32*E32 -> -5997.2468 | F31: ='Forecast Development'!F32*F32 -> -6497.6152 | G31: ='Forecast Development'!G32*G32 -> -7162.8271 | H31: ='Forecast Development'!H32*H32 -> -7883.6352 | I31: ='Forecast Development'!I32*I32 -> -8664.2241 | J31: =I31*$J$16 -> -8924.1508
A32: common size | B32: =B31/B$21 -> -0.2883001 | C32: =C31/C$21 -> -0.28199516 | D32: =D31/D$21 -> -0.2823767 | E32: -0.35 | F32: -0.348 | G32: -0.346 | H32: -0.344 | I32: -0.342
A33: rate of change | C33: =IF(ISERROR(C31/B31-1),"",C31/B31-1) -> 0.082149273 | D33: =IF(ISERROR(D31/C31-1),"",D31/C31-1) -> 0.16663792 | E33: Assume slight decline in store operating expense as a percent of company-operated store revenues.
A34: =Data!A69 -> <Other Operating Expenses> | B34: =Data!E69 -> -431.8 | C34: =Data!F69 -> -457.3 | D34: =Data!G69 -> -522.4 | E34: =('Forecast Development'!E39+'Forecast Development'!E46)*Forecasts!E35 -> -590.63621 | F34: =('Forecast Development'!F39+'Forecast Development'!F46)*Forecasts!F35 -> -649.89599 | G34: =('Forecast Development'!G39+'Forecast Development'!G46)*Forecasts!G35 -> -727.00605 | H34: =('Forecast Development'!H39+'Forecast Development'!H46)*Forecasts!H35 -> -811.43621 | I34: =('Forecast Development'!I39+'Forecast Development'!I46)*Forecasts!I35 -> -903.85587 | J34: =I34*$J$16 -> -930.97154
A35: common size | B35: =B34/B$21 -> -0.029044583 | C35: =C34/C$21 -> -0.02780311 | D35: =D34/D$21 -> -0.027261294 | E35: -0.13 | F35: =E35 -> -0.13 | G35: =F35 -> -0.13 | H35: =G35 -> -0.13 | I35: =H35 -> -0.13
A36: rate of change | C36: =IF(ISERROR(C34/B34-1),"",C34/B34-1) -> 0.059055118 | D36: =IF(ISERROR(D34/C34-1),"",D34/C34-1) -> 0.14235731 | E36: Assume steady percentage of licensed, CPG, Foodservice, and other revenues.
A37: =Data!A70 -> <Depreciation and Amortization> | B37: =Data!E70 -> -621.4 | C37: =Data!F70 -> -709.6 | D37: =Data!G70 -> -893.9 | E37: =-'Forecast Development'!E228*0.95 -> -1048.971 | F37: =-'Forecast Development'!F228*0.95 -> -1191.471 | G37: =-'Forecast Development'!G228*0.95 -> -1362.471 | H37: =-'Forecast Development'!H228*0.95 -> -1561.971 | I37: =-'Forecast Development'!I228*0.95 -> -1094.001 | J37: =I37*$J$16 -> -1126.821
A38: common size | B38: =B37/B$21 -> -0.041797831 | C38: =C37/C$21 -> -0.043142548 | D38: =D37/D$21 -> -0.046647915
A39: rate of change | C39: =IF(ISERROR(C37/B37-1),"",C37/B37-1) -> 0.14193756 | D39: =IF(ISERROR(D37/C37-1),"",D37/C37-1) -> 0.25972379 | E39: Amounts from depreciation schedule, Forecast Development worksheet.
A40: =Data!A71 -> <General and Administrative Expenses> | B40: =Data!E71 -> -937.9 | C40: =Data!F71 -> -991.3 | D40: =Data!G71 -> -1196.7 | E40: =E$21*E41 -> -1300.7008 | F40: =F$21*F41 -> -1420.2305 | G40: =G$21*G41 -> -1577.65 | H40: =H$21*H41 -> -1749.5617 | I40: =I$21*I41 -> -1937.2036 | J40: =I40*$J$16 -> -1995.3197
A41: common size | B41: =B40/B$21 -> -0.063086878 | C41: =C40/C$21 -> -0.060269459 | D41: =D40/D$21 -> -0.062449446 | E41: -0.06 | F41: =E41 -> -0.06 | G41: =F41 -> -0.06 | H41: =G41 -> -0.06 | I41: =H41 -> -0.06
A42: rate of change | C42: =IF(ISERROR(C40/B40-1),"",C40/B40-1) -> 0.056935707 | D42: =IF(ISERROR(D40/C40-1),"",D40/C40-1) -> 0.20720266 | E42: Assume steady state relative to revenues.
A43: =Data!A72 -> Other operating expenses (1) | B43: =Data!E72 -> 0 | C43: =Data!F72 -> 0 | D43: =Data!G72 -> 0 | E43: =E$21*E44 -> 0 | F43: =F$21*F44 -> 0 | G43: =G$21*G44 -> 0 | H43: =H$21*H44 -> 0 | I43: =I$21*I44 -> 0 | J43: =I43*$J$16 -> 0
A44: common size | B44: =B43/B$21 -> 0 | C44: =C43/C$21 -> 0 | D44: =D43/D$21 -> 0 | E44: 0 | F44: =E44 -> 0 | G44: =F44 -> 0 | H44: =G44 -> 0 | I44: =H44 -> 0
A45: rate of change | C45: =IF(ISERROR(C43/B43-1),"",C43/B43-1) | D45: =IF(ISERROR(D43/C43-1),"",D43/C43-1) | E45: Explain assumptions.
A46: =Data!A73 -> Other operating expenses (2) | B46: =Data!E73 -> 0 | C46: =Data!F73 -> 0 | D46: =Data!G73 -> 0 | E46: =E$21*E47 -> 0 | F46: =F$21*F47 -> 0 | G46: =G$21*G47 -> 0 | H46: =H$21*H47 -> 0 | I46: =I$21*I47 -> 0 | J46: =I46*$J$16 -> 0
A47: common size | B47: =B46/B$21 -> 0 | C47: =C46/C$21 -> 0 | D47: =D46/D$21 -> 0 | E47: 0 | F47: =E47 -> 0 | G47: =F47 -> 0 | H47: =G47 -> 0 | I47: =H47 -> 0
A48: rate of change | C48: =IF(ISERROR(C46/B46-1),"",C46/B46-1) | D48: =IF(ISERROR(D46/C46-1),"",D46/C46-1) | E48: Explain assumptions.
A49: =Data!A74 -> Income from Equity Investees | B49: =Data!E74 -> 251.4 | C49: =Data!F74 -> 268.3 | D49: =Data!G74 -> 249.9 | E49: =((D145+E145)/2)*E50 -> 180.4 | F49: =((E145+F145)/2)*F50 -> 189.42 | G49: =((F145+G145)/2)*G50 -> 198.891 | H49: =((G145+H145)/2)*H50 -> 208.83555 | I49: =((H145+I145)/2)*I50 -> 219.27733 | J49: =I49*$J$16 -> 225.85565
A50: common size | B50: =B49/B$21 -> 0.016910162 | C50: =C49/C$21 -> 0.016312212 | D50: =D49/D$21 -> 0.01304096 | E50: 0.5 | F50: =E50 -> 0.5 | G50: =F50 -> 0.5 | H50: =G50 -> 0.5 | I50: =H50 -> 0.5
A51: rate of change | C51: =IF(ISERROR(C49/B49-1),"",C49/B49-1) -> 0.067223548 | D51: =IF(ISERROR(D49/C49-1),"",D49/C49-1) -> -0.068579948 | E51: Assume 50% rate of return from equity investees.
A52: =Data!A75 -> Non-recurring operating gains <losses> | B52: =Data!E75 -> -2784.1 | C52: =Data!F75 -> 20.2 | D52: =Data!G75 -> 0 | E52: 0 | F52: 0 | G52: 0 | H52: 0 | I52: 0 | J52: =I52*$J$16 -> 0
A53: common size | B53: =B52/B$21 -> -0.18726962 | C53: =C52/C$21 -> 0.0012281278 | D53: =D52/D$21 -> 0 | E53: 0 | F53: =E53 -> 0 | G53: =F53 -> 0 | H53: =G53 -> 0 | I53: =H53 -> 0
A54: rate of change | C54: =IF(ISERROR(C52/B52-1),"",C52/B52-1) -> -1.0072555 | D54: =IF(ISERROR(D52/C52-1),"",D52/C52-1) -> -1 | E54: Explain assumptions
A55: =Data!A76 -> Operating Profit | B55: =B27+B31+B34+B37+B40+B43+B46+B49+B52 -> -325.4 | C55: =C27+C31+C34+C37+C40+C43+C46+C49+C52 -> 3081.1 | D55: =D27+D31+D34+D37+D40+D43+D46+D49+D52 -> 3601 | E55: =E27+E31+E34+E37+E40+E43+E46+E49+E52 -> 4267.6977 | F55: =F27+F31+F34+F37+F40+F43+F46+F49+F52 -> 4710.3603 | G55: =G27+G31+G34+G37+G40+G43+G46+G49+G52 -> 5326.4155 | H55: =H27+H31+H34+H37+H40+H43+H46+H49+H52 -> 6002.9166 | I55: =I27+I31+I34+I37+I40+I43+I46+I49+I52 -> 7444.7705 | J55: =J27+J31+J34+J37+J40+J43+J46+J49+J52 -> 7668.1136
A56: common size | B56: =B55/B$21 -> -0.021887696 | C56: =C55/C$21 -> 0.18732596 | D56: =D55/D$21 -> 0.18791715 | E56: =E55/E$21 -> 0.19686454 | F56: =F55/F$21 -> 0.19899701 | G56: =G55/G$21 -> 0.20257023 | H56: =H55/H$21 -> 0.20586585 | I56: =I55/I$21 -> 0.23058301 | J56: =J55/J$21 -> 0.23058301
A57: rate of change | C57: =IF(ISERROR(C55/B55-1),"",C55/B55-1) -> -10.468654 | D57: =IF(ISERROR(D55/C55-1),"",D55/C55-1) -> 0.16873844 | E57: =IF(ISERROR(E55/D55-1),"",E55/D55-1) -> 0.18514238 | F57: =IF(ISERROR(F55/E55-1),"",F55/E55-1) -> 0.10372398 | G57: =IF(ISERROR(G55/F55-1),"",G55/F55-1) -> 0.13078728 | H57: =IF(ISERROR(H55/G55-1),"",H55/G55-1) -> 0.12700869 | I57: =IF(ISERROR(I55/H55-1),"",I55/H55-1) -> 0.24019223
A59: =Data!A77 -> Interest income | B59: =Data!E77 -> 123.6 | C59: =Data!F77 -> 142.7 | D59: =Data!G77 -> 43 | E59: =E60*((D115+E115+D118+E118+D142+E142)/2) -> 43.168607 | F59: =F60*((E115+F115+E118+F118+E142+F142)/2) -> 47.782345 | G59: =G60*((F115+G115+F118+G118+F142+G142)/2) -> 52.025231 | H59: =H60*((G115+H115+G118+H118+G142+H142)/2) -> 57.029337 | I59: =I60*((H115+I115+H118+I118+H142+I142)/2) -> 62.476164 | J59: =I59*$J$16 -> 64.350449
A60: common size | B60: =B59/B$21 -> 0.0083138268 | C60: =C59/C$21 -> 0.0086759323 | D60: =D59/D$21 -> 0.0022439427 | E60: 0.021 | F60: =E60 -> 0.021 | G60: =F60 -> 0.021 | H60: =G60 -> 0.021 | I60: =H60 -> 0.021
A61: rate of change | C61: =IF(ISERROR(C59/B59-1),"",C59/B59-1) -> 0.15453074 | D61: =IF(ISERROR(D59/C59-1),"",D59/C59-1) -> -0.69866854 | E61: Interest rate earned on average balance in cash and investment securities.
A62: =Data!A78 -> <Interest expense> | B62: =Data!E78 -> -28.1 | C62: =Data!F78 -> -64.1 | D62: =Data!G78 -> -70.5 | E62: =E63*((D177+E177+D180+E180+D198+E198)/2) -> -77.07375 | F62: =F63*((E177+F177+E180+F180+E198+F198)/2) -> -90.607332 | G62: =G63*((F177+G177+F180+G180+F198+G198)/2) -> -90.607332 | H62: =H63*((G177+H177+G180+H180+G198+H198)/2) -> -90.607332 | I62: =I63*((H177+I177+H180+I180+H198+I198)/2) -> -90.607332 | J62: =I62*$J$16 -> -93.325552
A63: common size | B63: =B62/B$21 -> -0.0018901176 | C63: =C62/C$21 -> -0.0038971777 | D63: =D62/D$21 -> -0.0036790223 | E63: =-'Forecast Development'!E257 -> -0.027067164 | F63: =E63 -> -0.027067164 | G63: =F63 -> -0.027067164 | H63: =G63 -> -0.027067164 | I63: =H63 -> -0.027067164
A64: rate of change | C64: =IF(ISERROR(C62/B62-1),"",C62/B62-1) -> 1.2811388 | D64: =IF(ISERROR(D62/C62-1),"",D62/C62-1) -> 0.099843994 | E64: Weighted average interest rate on average balance in financial liabilities. See Forecast Development.
A65: =Data!A79 -> Income <Loss> from equity affiliates | B65: =Data!E79 -> 0 | C65: =Data!F79 -> 0 | D65: =Data!G79 -> 0 | E65: =E66*(D142+E142)/2 -> 0 | F65: =F66*(E142+F142)/2 -> 0 | G65: =G66*(F142+G142)/2 -> 0 | H65: =H66*(G142+H142)/2 -> 0 | I65: =I66*(H142+I142)/2 -> 0 | J65: =I65*$J$16 -> 0
A66: common size | B66: =B65/B$21 -> 0 | C66: =C65/C$21 -> 0 | D66: =D65/D$21 -> 0
A67: rate of change | C67: =IF(ISERROR(C65/B65-1),"",C65/B65-1) | D67: =IF(ISERROR(D65/C65-1),"",D65/C65-1) | E67: Explain assumptions
A68: =Data!A80 -> Other income or gains <Other expenses or losses> | B68: =Data!E80 -> 0 | C68: =Data!F80 -> 0 | D68: =Data!G80 -> 329.5 | E68: 0 | F68: 0 | G68: 0 | H68: 0 | I68: 0 | J68: =I68*$J$16 -> 0
A69: common size | B69: =B68/B$21 -> 0 | C69: =C68/C$21 -> 0 | D69: =D68/D$21 -> 0.017194863 | E69: 0 | F69: =E69 -> 0 | G69: =F69 -> 0 | H69: =G69 -> 0 | I69: =H69 -> 0
A70: rate of change | C70: =IF(ISERROR(C68/B68-1),"",C68/B68-1) | D70: =IF(ISERROR(D68/C68-1),"",D68/C68-1) | E70: Explain assumptions
A71: =Data!A81 -> Income before Tax | B71: =B55+B59+B62+B65+B68 -> -229.9 | C71: =C55+C59+C62+C65+C68 -> 3159.7 | D71: =D55+D59+D62+D65+D68 -> 3903 | E71: =E55+E59+E62+E65+E68 -> 4233.7926 | F71: =F55+F59+F62+F65+F68 -> 4667.5353 | G71: =G55+G59+G62+G65+G68 -> 5287.8334 | H71: =H55+H59+H62+H65+H68 -> 5969.3386 | I71: =I55+I59+I62+I65+I68 -> 7416.6393 | J71: =J55+J59+J62+J65+J68 -> 7639.1385
A72: common size | B72: =B71/B$21 -> -0.015463987 | C72: =C71/C$21 -> 0.19210472 | D72: =D71/D$21 -> 0.20367693 | E72: =E71/E$21 -> 0.19530053 | F72: =F71/F$21 -> 0.1971878 | G72: =G71/G$21 -> 0.20110291 | H72: =H71/H$21 -> 0.20471431 | I72: =I71/I$21 -> 0.22971172 | J72: =J71/J$21 -> 0.22971172
A73: rate of change | C73: =IF(ISERROR(C71/B71-1),"",C71/B71-1) -> -14.743802 | D73: =IF(ISERROR(D71/C71-1),"",D71/C71-1) -> 0.23524385 | E73: =IF(ISERROR(E71/D71-1),"",E71/D71-1) -> 0.084753411 | F73: =IF(ISERROR(F71/E71-1),"",F71/E71-1) -> 0.1024478 | G73: =IF(ISERROR(G71/F71-1),"",G71/F71-1) -> 0.13289628 | H73: =IF(ISERROR(H71/G71-1),"",H71/G71-1) -> 0.12888174 | I73: =IF(ISERROR(I71/H71-1),"",I71/H71-1) -> 0.2424558
A75: =Data!A82 -> <Income tax expense> | B75: =Data!E82 -> 238.7 | C75: =Data!F82 -> -1092 | D75: =Data!G82 -> -1143.7 | E75: =E71*E76 -> -1439.4895 | F75: =F71*F76 -> -1586.962 | G75: =G71*G76 -> -1797.8634 | H75: =H71*H76 -> -2029.5751 | I75: =I71*I76 -> -2521.6574 | J75: =I75*$J$16 -> -2597.3071
A76: common size | B76: =B75/B$21 -> 0.01605591 | C76: =C75/C$21 -> -0.066391858 | D76: =D75/D$21 -> -0.059683656 | E76: -0.34 | F76: =E76 -> -0.34 | G76: =F76 -> -0.34 | H76: =G76 -> -0.34 | I76: =H76 -> -0.34
A77: rate of change | C77: =IF(ISERROR(C75/B75-1),"",C75/B75-1) -> -5.5747801 | D77: =IF(ISERROR(D75/C75-1),"",D75/C75-1) -> 0.047344322 | E77: Effective income tax rate assumptions.
A78: =Data!A83 -> Income <Loss> from discontinued operations | B78: =Data!E83 -> 0 | C78: =Data!F83 -> 0 | D78: =Data!G83 -> 0 | E78: 0 | F78: 0 | G78: 0 | H78: 0 | I78: 0 | J78: =I78*$J$16 -> 0
A79: common size | B79: =B78/B$21 -> 0 | C79: =C78/C$21 -> 0 | D79: =D78/D$21 -> 0 | E79: 0 | F79: =E79 -> 0 | G79: =F79 -> 0 | H79: =G79 -> 0 | I79: =H79 -> 0
A80: rate of change | C80: =IF(ISERROR(C78/B78-1),"",C78/B78-1) | D80: =IF(ISERROR(D78/C78-1),"",D78/C78-1) | E80: Explain assumptions
A81: =Data!A85 -> Changes in accounting principles | B81: =Data!E85 -> 0 | C81: =Data!F85 -> 0 | D81: =Data!G85 -> 0 | E81: 0 | F81: 0 | G81: 0 | H81: 0 | I81: 0 | J81: =I81*$J$16 -> 0
A82: common size | B82: =B81/B$21 -> 0 | C82: =C81/C$21 -> 0 | D82: =D81/D$21 -> 0 | E82: 0 | F82: =E82 -> 0 | G82: =F82 -> 0 | H82: =G82 -> 0 | I82: =H82 -> 0
A83: rate of change | C83: =IF(ISERROR(C81/B81-1),"",C81/B81-1) | D83: =IF(ISERROR(D81/C81-1),"",D81/C81-1) | E83: Explain assumptions
A84: =Data!A86 -> Net Income | B84: =B71+B75+B78+B81 -> 8.8 | C84: =C71+C75+C78+C81 -> 2067.7 | D84: =D71+D75+D78+D81 -> 2759.3 | E84: =E71+E75+E78+E81 -> 2794.3031 | F84: =F71+F75+F78+F81 -> 3080.5733 | G84: =G71+G75+G78+G81 -> 3489.97 | H84: =H71+H75+H78+H81 -> 3939.7635 | I84: =I71+I75+I78+I81 -> 4894.9819 | J84: =J71+J75+J78+J81 -> 5041.8314
A85: common size | B85: =B84/B$21 -> 0.00059192294 | C85: =C84/C$21 -> 0.12571286 | D85: =D84/D$21 -> 0.14399328 | E85: =E84/E$21 -> 0.12889835 | F85: =F84/F$21 -> 0.13014395 | G85: =G84/G$21 -> 0.13272792 | H85: =H84/H$21 -> 0.13511145 | I85: =I84/I$21 -> 0.15160973 | J85: =J84/J$21 -> 0.15160973
A86: rate of change | C86: =IF(ISERROR(C84/B84-1),"",C84/B84-1) -> 233.96591 | D86: =IF(ISERROR(D84/C84-1),"",D84/C84-1) -> 0.33447792 | E86: =IF(ISERROR(E84/D84-1),"",E84/D84-1) -> 0.012685497 | F86: =IF(ISERROR(F84/E84-1),"",F84/E84-1) -> 0.1024478 | G86: =IF(ISERROR(G84/F84-1),"",G84/F84-1) -> 0.13289628 | H86: =IF(ISERROR(H84/G84-1),"",H84/G84-1) -> 0.12888174 | I86: =IF(ISERROR(I84/H84-1),"",I84/H84-1) -> 0.2424558 | J86: =IF(ISERROR(J84/I84-1),"",J84/I84-1) -> 0.03
A87: =Data!A87 -> Net income attributable to noncontrolling interests | B87: =Data!E87 -> -0.5 | C87: =Data!F87 -> 0.4 | D87: =Data!G87 -> -1.9 | E87: =-E88*D237 -> 0 | F87: =-F88*E237 -> 0 | G87: =-G88*F237 -> 0 | H87: =-H88*G237 -> 0 | I87: =-I88*H237 -> 0 | J87: =I87*$J$16 -> 0
A88: common size | B88: =B87/B$21 -> -3.3631985e-05 | C88: =C87/C$21 -> 2.4319362e-05 | D88: =D87/D$21 -> -9.9150955e-05 | E88: 0 | F88: =E88 -> 0 | G88: =F88 -> 0 | H88: =G88 -> 0 | I88: =H88 -> 0
A89: rate of change | C89: =IF(ISERROR(C87/B87-1),"",C87/B87-1) -> -1.8 | D89: =IF(ISERROR(D87/C87-1),"",D87/C87-1) -> -5.75 | E89: Assume noncontrolling interests are acquired.
A90: =Data!A88 -> Net Income attributable to common shareholders | B90: =B84+B87 -> 8.3 | C90: =C84+C87 -> 2068.1 | D90: =D84+D87 -> 2757.4 | E90: =E84+E87 -> 2794.3031 | F90: =F84+F87 -> 3080.5733 | G90: =G84+G87 -> 3489.97 | H90: =H84+H87 -> 3939.7635 | I90: =I84+I87 -> 4894.9819 | J90: =J84+J87 -> 5041.8314
A91: common size | B91: =B90/B$21 -> 0.00055829096 | C91: =C90/C$21 -> 0.12573718 | D91: =D90/D$21 -> 0.14389413 | E91: =E90/E$21 -> 0.12889835 | F91: =F90/F$21 -> 0.13014395 | G91: =G90/G$21 -> 0.13272792 | H91: =H90/H$21 -> 0.13511145 | I91: =I90/I$21 -> 0.15160973 | J91: =J90/J$21 -> 0.15160973
A92: rate of change | C92: =IF(ISERROR(C90/B90-1),"",C90/B90-1) -> 248.16867 | D92: =IF(ISERROR(D90/C90-1),"",D90/C90-1) -> 0.3333011 | E92: =IF(ISERROR(E90/D90-1),"",E90/D90-1) -> 0.013383293 | F92: =IF(ISERROR(F90/E90-1),"",F90/E90-1) -> 0.1024478 | G92: =IF(ISERROR(G90/F90-1),"",G90/F90-1) -> 0.13289628 | H92: =IF(ISERROR(H90/G90-1),"",H90/G90-1) -> 0.12888174 | I92: =IF(ISERROR(I90/H90-1),"",I90/H90-1) -> 0.2424558 | J92: =IF(ISERROR(J90/I90-1),"",J90/I90-1) -> 0.03
A94: =Data!A91 -> Other comprehensive income items | B94: =Data!E91 -> 43.8 | C94: =Data!F91 -> -41.3 | D94: =Data!G91 -> -195.5 | E94: 0 | F94: 0 | G94: 0 | H94: 0 | I94: 0 | J94: =I94*$J$16 -> 0
A95: common size | B95: =B94/B$21 -> 0.0029461619 | C95: =C94/C$21 -> -0.0025109741 | D95: =D94/D$21 -> -0.010202111 | E95: 0 | F95: =E95 -> 0 | G95: =F95 -> 0 | H95: =G95 -> 0 | I95: =H95 -> 0
A96: rate of change | C96: =IF(ISERROR(C94/B94-1),"",C94/B94-1) -> -1.9429224 | D96: =IF(ISERROR(D94/C94-1),"",D94/C94-1) -> 3.7336562 | E96: Assume random walk, mean zero.
A97: =Data!A92 -> Comprehensive Income | B97: =B84+B94 -> 52.6 | C97: =C84+C94 -> 2026.4 | D97: =D84+D94 -> 2563.8 | E97: =E84+E94 -> 2794.3031 | F97: =F84+F94 -> 3080.5733 | G97: =G84+G94 -> 3489.97 | H97: =H84+H94 -> 3939.7635 | I97: =I84+I94 -> 4894.9819 | J97: =J84+J94 -> 5041.8314
A98: common size | B98: =B97/B$21 -> 0.0035380849 | C98: =C97/C$21 -> 0.12320189 | D98: =D97/D$21 -> 0.13379117 | E98: =E97/E$21 -> 0.12889835 | F98: =F97/F$21 -> 0.13014395 | G98: =G97/G$21 -> 0.13272792 | H98: =H97/H$21 -> 0.13511145 | I98: =I97/I$21 -> 0.15160973 | J98: =J97/J$21 -> 0.15160973
A99: rate of change | C99: =IF(ISERROR(C97/B97-1),"",C97/B97-1) -> 37.524715 | D99: =IF(ISERROR(D97/C97-1),"",D97/C97-1) -> 0.26519937 | E99: =IF(ISERROR(E97/D97-1),"",E97/D97-1) -> 0.089906814 | F99: =IF(ISERROR(F97/E97-1),"",F97/E97-1) -> 0.1024478 | G99: =IF(ISERROR(G97/F97-1),"",G97/F97-1) -> 0.13289628 | H99: =IF(ISERROR(H97/G97-1),"",H97/G97-1) -> 0.12888174 | I99: =IF(ISERROR(I97/H97-1),"",I97/H97-1) -> 0.2424558 | J99: =IF(ISERROR(J97/I97-1),"",J97/I97-1) -> 0.03
A102: FSAP OUTPUT: | B102: FINANCIAL STATEMENT FORECASTS
A103: =Data!A9 -> Analyst Name: | B103: =Data!B9 -> Wahlen, Baginski & Bradshaw
A104: =Data!A10 -> Company Name: | B104: =Data!B10 -> Starbucks
B106: Row Format: | E106: Row Format:
B107: Actual Amounts | E107: Forecast Amounts | J107: Year +6 and beyond:
B108: Common Size Percent | E108: Forecast assumption | I108: Long-Run Growth Rate: | J108: =$J$15 -> 0.03
B109: Rate of Change Percent | E109: Forecast assumption explanation | I109: Long-Run Growth Factor: | J109: =1+$J$15 -> 1.03
B111: Actuals | E111: Forecasts | L111: A Comment on Entering Forecast Assumptions:
B112: =B19 -> 2013 | C112: =C19 -> 2014 | D112: =D19 -> 2015 | E112: =E$19 -> Year +1 | F112: =F$19 -> Year +2 | G112: =G$19 -> Year +3 | H112: =H$19 -> Year +4 | I112: =I$19 -> Year +5 | J112: =J$19 -> Year +6 | L112: This worksheet allows the FSAP user to build forecasts of future income statements, balance sheets, and statements of cash flows. FSAP automatically enters data from the DATA spreadsheet for the most recent three years in columns B, C, and D. This worksheet allows the user flexibility to compute forecast amounts for each income statement and balance sheet account. For each account, the user should enter the forecast computations in the first row (highlighted in green with bold blue font). In the second row for each account, the user can enter forecast assumption parameters (such as growth rates or percentages) to be used in the forecast computations. In the third row for each account, the user can enter a brief explanatory note to explain the forecast assumptions. The FSAP user can also develop more detailed computations of forecast amounts in the Forecast Development worksheet, and incorporate those forecast amounts by referencing them here in the Forecasts worksheet.
...

Sheet Forecast Development
A1: =Data!A1 -> Financial Statement Analysis Package (FSAP): Version 9.0
A2: =Data!A2 -> Financial Reporting, Financial Statement Analysis, and Valuation: A Strategic Perspective, 9th Edition | K2: FSAP User Guides:
A3: By James Wahlen, Steve Baginski and Mark Bradshaw
K4: The FSAP user should only enter data in the blue-font cells shaded light green.
A6: The FSAP User Guides appear in column K to the right. | K6: Forecast Development:
K7: This Forecast Development spreadsheet provides work space in which the analyst can:
K8: - build detailed Revenues revenue forecasts
K9: - build forecasts of capital expenditures, property, plant and equipment, depreciation expense, and accumulated depreciation.
K10: - build detailed forecasts of other financial statement amounts.
A11: Analyst Name: | B11: =Data!B9 -> Wahlen, Baginski & Bradshaw
A12: Company Name: | B12: =Data!B10 -> Starbucks
K13: It is not necessary to use this spreadsheet to build financial statement forecasts in the FSAP Forecasts
K14: spreadsheet. If you use this spreadsheet to build more detailed forecasts, the you will need to link these
K15: forecast amounts to the appropriate cells in the financial statements in the FSAP Forecasts spreadsheet.
A16: Revenue Forecast Development
B18: Actuals | E18: Forecasts
A19: Year | B19: =Forecasts!B19 -> 2013 | C19: =Forecasts!C19 -> 2014 | D19: =Forecasts!D19 -> 2015 | E19: =Forecasts!E19 -> Year +1 | F19: =Forecasts!F19 -> Year +2 | G19: =Forecasts!G19 -> Year +3 | H19: =Forecasts!H19 -> Year +4 | I19: =Forecasts!I19 -> Year +5
A21: Net Revenues (in millions):
A22: Company-operated stores | B22: =B32 -> 11802.7 | C22: =C32 -> 12983 | D22: =D32 -> 15203.2 | E22: =E32 -> 17134.991 | F22: =F32 -> 18671.308 | G22: =G32 -> 20701.812 | H22: =H32 -> 22917.544 | I22: =I32 -> 25333.988
A23: Licensed stores | B23: =B39 -> 1351 | C23: =C39 -> 1583.5 | D23: =D39 -> 1856 | E23: =E39 -> 2185.0084 | F23: =F39 -> 2453.965 | G23: =G39 -> 2792.5958 | H23: =H39 -> 3162.0826 | I23: =I39 -> 3565.0297
A24: CPG, foodservice and other | B24: =B46 -> 1713.1 | C24: =C46 -> 1881.3 | D24: =D46 -> 2103.5 | E24: =E46 -> 2358.3471 | F24: =F46 -> 2545.235 | G24: =G46 -> 2799.7585 | H24: =H46 -> 3079.7344 | I24: =I46 -> 3387.7078
A25: Total Net Revenues | B25: =SUM(B22:B24) -> 14866.8 | C25: =SUM(C22:C24) -> 16447.8 | D25: =SUM(D22:D24) -> 19162.7 | E25: =SUM(E22:E24) -> 21678.346 | F25: =SUM(F22:F24) -> 23670.508 | G25: =SUM(G22:G24) -> 26294.167 | H25: =SUM(H22:H24) -> 29159.361 | I25: =SUM(I22:I24) -> 32286.726 | K25: This revenue forecast development schedule was developed specifically for Starbucks. FSAP users who wish to develop detailed revenues forecasts of other firms should adapt this schedule as necessary to incorporate the other firms' various soruces of revenue.
A26: rate of change | C26: =C25/B25-1 -> 0.10634434 | D26: =D25/C25-1 -> 0.16506159 | E26: =E25/D25-1 -> 0.13127829 | F26: =F25/E25-1 -> 0.091896381 | G26: =G25/F25-1 -> 0.11084083 | H26: =H25/G25-1 -> 0.10896692 | I26: =I25/H25-1 -> 0.1072508
E27: Implied revenue growth rates.
A29: Summary: Revenues by Segment and Type: | E29: Starbucks: Revenue Forecasts by Segment and Type
B30: =B19 -> 2013 | C30: =C19 -> 2014 | D30: =D19 -> 2015 | E30: =E19 -> Year +1 | F30: =F19 -> Year +2 | G30: =G19 -> Year +3 | H30: =H19 -> Year +4 | I30: =I19 -> Year +5
A32: Company-operated stores | B32: =B63 -> 11802.7 | C32: =C63 -> 12983 | D32: =D63 -> 15203.2 | E32: =E63 -> 17134.991 | F32: =F63 -> 18671.308 | G32: =G63 -> 20701.812 | H32: =H63 -> 22917.544 | I32: =I63 -> 25333.988
A33: Growth rates | C33: =C32/B32-1 -> 0.10000254 | D33: =D32/C32-1 -> 0.17100824 | E33: =E32/D32-1 -> 0.12706476 | F33: =F32/E32-1 -> 0.089659641 | G33: =G32/F32-1 -> 0.10874998 | H33: =H32/G32-1 -> 0.10703081 | I33: =I32/H32-1 -> 0.10544081
A34: Number of company stores | B34: =B95+B118+B142+B166 -> 10143 | C34: =C95+C118+C142+C166 -> 10713 | D34: =D95+D118+D142+D166 -> 12235 | E34: =E95+E118+E142+E166 -> 12885 | F34: =F95+F118+F142+F166 -> 13535 | G34: =G95+G118+G142+G166 -> 14185 | H34: =H95+H118+H142+H166 -> 14835 | I34: =I95+I118+I142+I166 -> 15485
A35: Revenues/Average Store | B35: 1.0071914 | C35: =C32/((B34+C34)/2) -> 1.2450134 | D35: =D32/((C34+D34)/2) -> 1.3250131 | E35: =E32/((D34+E34)/2) -> 1.3642509 | F35: =F32/((E34+F34)/2) -> 1.4134223 | G35: =G32/((F34+G34)/2) -> 1.4936373 | H35: =H32/((G34+H34)/2) -> 1.579431 | I35: =I32/((H34+I34)/2) -> 1.6711074
A36: Revenue Growth/Average Store | C36: =C35/B35-1 -> 0.23612394 | D36: =D35/C35-1 -> 0.064256052 | E36: =E35/D35-1 -> 0.02961314 | F36: =F35/E35-1 -> 0.036042777 | G36: =G35/F35-1 -> 0.056752326 | H36: =H35/G35-1 -> 0.05743949 | I36: =I35/H35-1 -> 0.058043937
A39: Licensing | B39: =B72 -> 1351 | C39: =C72 -> 1583.5 | D39: =D72 -> 1856 | E39: =E72 -> 2185.0084 | F39: =F72 -> 2453.965 | G39: =G72 -> 2792.5958 | H39: =H72 -> 3162.0826 | I39: =I72 -> 3565.0297
A40: Growth rates | C40: =C39/B39-1 -> 0.17209474 | D40: =D39/C39-1 -> 0.17208715 | E40: =E39/D39-1 -> 0.17726745 | F40: =F39/E39-1 -> 0.12309178 | G40: =G39/F39-1 -> 0.13799333 | H40: =H39/G39-1 -> 0.13230948 | I40: =I39/H39-1 -> 0.12743089
A41: Number of licensed stores | B41: =B96+B119+B143+B167 -> 9624 | C41: =C96+C119+C143+C167 -> 10653 | D41: =D96+D119+D143+D167 -> 10808 | E41: =E96+E119+E143+E167 -> 11958 | F41: =F96+F119+F143+F167 -> 13108 | G41: =G96+G119+G143+G167 -> 14258 | H41: =H96+H119+H143+H167 -> 15408 | I41: =I96+I119+I143+I167 -> 16558
A42: Revenues/Average Store | B42: 0.11153307 | C42: =C39/((C41+B41)/2) -> 0.15618681 | D42: =D39/((D41+C41)/2) -> 0.17296491 | E42: =E39/((E41+D41)/2) -> 0.19195365 | F42: =F39/((F41+E41)/2) -> 0.19580028 | G42: =G39/((G41+F41)/2) -> 0.20409236 | H42: =H39/((H41+G41)/2) -> 0.2131789 | I42: =I39/((I41+H41)/2) -> 0.22305135
A43: Revenue Growth/Average Store | C43: =C42/B42-1 -> 0.40036325 | D43: =D42/C42-1 -> 0.10742328 | E43: =E42/D42-1 -> 0.10978374 | F43: =F42/E42-1 -> 0.020039397 | G43: =G42/F42-1 -> 0.042349659 | H43: =H42/G42-1 -> 0.044521719 | I43: =I42/H42-1 -> 0.046310605
A46: CPG, Foodservice and Other | B46: =B78 -> 1713.1 | C46: =C78 -> 1881.3 | D46: =D78 -> 2103.5 | E46: =E78 -> 2358.3471 | F46: =F78 -> 2545.235 | G46: =G78 -> 2799.7585 | H46: =H78 -> 3079.7344 | I46: =I78 -> 3387.7078
A47: Growth rates | C47: =C46/B46-1 -> 0.098184578 | D47: =D46/C46-1 -> 0.11810982 | E47: =E46/D46-1 -> 0.12115385 | F47: =F46/E46-1 -> 0.079245283 | G47: =G46/F46-1 -> 0.1 | H47: =H46/G46-1 -> 0.1 | I47: =I46/H46-1 -> 0.1
A50: Revenues | B50: =B32+B39+B46 -> 14866.8 | C50: =C32+C39+C46 -> 16447.8 | D50: =D32+D39+D46 -> 19162.7 | E50: =E32+E39+E46 -> 21678.346 | F50: =F32+F39+F46 -> 23670.508 | G50: =G32+G39+G46 -> 26294.167 | H50: =H32+H39+H46 -> 29159.361 | I50: =I32+I39+I46 -> 32286.726
A54: Starbucks' Combined Revenue Forecasts
B55: Actuals: | E55: Projections:
A56: Company Operated Stores: | B56: 2013 | C56: 2014 | D56: 2015 | E56: Year +1 | F56: Year +2 | G56: Year +3 | H56: Year +4 | I56: Year +5
A57: Americas: | B57: =B100 -> 10038.3 | C57: =C100 -> 10866.5 | D57: =D100 -> 11925.6 | E57: =E100 -> 13104.827 | F57: =F100 -> 14440.731 | G57: =G100 -> 15889.767 | H57: =H100 -> 17460.7 | I57: =I100 -> 19162.941
A58: CAP: | B58: =B123 -> 671.7 | C58: =C123 -> 859.4 | D58: =D123 -> 2127.3 | E58: =E123 -> 2579.012 | F58: =F123 -> 3077.7069 | G58: =G123 -> 3633.5819 | H58: =H123 -> 4252.1986 | I58: =I123 -> 4939.6172
A59: EMEA: | B59: =B147 -> 932.8 | C59: =C147 -> 1013.8 | D59: =D147 -> 911.2 | E59: =E147 -> 881.5772 | F59: =F147 -> 899.20875 | G59: =G147 -> 917.19292 | H59: =H147 -> 935.53678 | I59: =I147 -> 954.24752
A60: Other Stores: | B60: =B170 -> 159.9 | C60: =C170 -> 243.3 | D60: =D170 -> 239.1 | E60: =E170 -> 246.273 | F60: =F170 -> 253.66119 | G60: =G170 -> 261.27103 | H60: =H170 -> 269.10916 | I60: =I170 -> 277.18243
A61: Subtotals: | B61: =SUM(B57:B60) -> 11802.7 | C61: =SUM(C57:C60) -> 12983 | D61: =SUM(D57:D60) -> 15203.2 | E61: =SUM(E57:E60) -> 16811.689 | F61: =SUM(F57:F60) -> 18671.308 | G61: =SUM(G57:G60) -> 20701.812 | H61: =SUM(H57:H60) -> 22917.544 | I61: =SUM(I57:I60) -> 25333.988
A62: The 53rd Week Effect (53/52): | E62: =53/52 -> 1.0192308
A63: Totals: | B63: =B61 -> 11802.7 | C63: =C61 -> 12983 | D63: =D61 -> 15203.2 | E63: =E61*E62 -> 17134.991 | F63: =F61 -> 18671.308 | G63: =G61 -> 20701.812 | H63: =H61 -> 22917.544 | I63: =I61 -> 25333.988
A66: Licensed Stores: | B66: =B56 -> 2013 | C66: =C56 -> 2014 | D66: =D56 -> 2015 | E66: =E56 -> Year +1 | F66: =F56 -> Year +2 | G66: =G56 -> Year +3 | H66: =H56 -> Year +4 | I66: =I56 -> Year +5
A67: Americas: | B67: =B105 -> 915.4 | C67: =C105 -> 1074.9 | D67: =D105 -> 1334.4 | E67: =E105 -> 1495.8123 | F67: =F105 -> 1673.55 | G67: =G105 -> 1867.2313 | H67: =H105 -> 2078.1295 | I67: =I105 -> 2307.6136
A68: CAP: | B68: =B128 -> 245.3 | C68: =C128 -> 270.2 | D68: =D128 -> 264.4 | E68: =E128 -> 340.9523 | F68: =F128 -> 430.94928 | G68: =G128 -> 531.87518 | H68: =H128 -> 644.81905 | I68: =I128 -> 770.96887
A69: EMEA: | B69: =B152 -> 190.3 | C69: =C152 -> 238.4 | D69: =D152 -> 257.2 | E69: =E152 -> 307.01723 | F69: =F152 -> 349.4657 | G69: =G152 -> 393.4893 | H69: =H152 -> 439.13406 | I69: =I152 -> 486.44722
A70: Subtotals: | B70: =SUM(B67:B69) -> 1351 | C70: =SUM(C67:C69) -> 1583.5 | D70: =SUM(D67:D69) -> 1856 | E70: =SUM(E67:E69) -> 2143.7818 | F70: =SUM(F67:F69) -> 2453.965 | G70: =SUM(G67:G69) -> 2792.5958 | H70: =SUM(H67:H69) -> 3162.0826 | I70: =SUM(I67:I69) -> 3565.0297
A71: The 53rd Week Effect (53/52): | E71: =53/52 -> 1.0192308
A72: Totals: | B72: =B70 -> 1351 | C72: =C70 -> 1583.5 | D72: =D70 -> 1856 | E72: =E70*E71 -> 2185.0084 | F72: =F70 -> 2453.965 | G72: =G70 -> 2792.5958 | H72: =H70 -> 3162.0826 | I72: =I70 -> 3565.0297
A75: CPG, Foodservice, and Other: | B75: =B66 -> 2013 | C75: =C66 -> 2014 | D75: =D66 -> 2015 | E75: =E66 -> Year +1 | F75: =F66 -> Year +2 | G75: =G66 -> Year +3 | H75: =H66 -> Year +4 | I75: =I66 -> Year +5
A76: Revenues: | B76: =B176 -> 1713.1 | C76: =C176 -> 1881.3 | D76: =D176 -> 2103.5 | E76: =E176 -> 2313.85 | F76: =F176 -> 2545.235 | G76: =G176 -> 2799.7585 | H76: =H176 -> 3079.7344 | I76: =I176 -> 3387.7078
A77: The 53rd Week Effect (53/52): | E77: =53/52 -> 1.0192308
A78: Totals: | B78: =B76 -> 1713.1 | C78: =C76 -> 1881.3 | D78: =D76 -> 2103.5 | E78: =E76*E77 -> 2358.3471 | F78: =F76 -> 2545.235 | G78: =G76 -> 2799.7585 | H78: =H76 -> 3079.7344 | I78: =I76 -> 3387.7078
A81: Total Net Revenues: | B81: =B63+B72+B78 -> 14866.8 | C81: =C63+C72+C78 -> 16447.8 | D81: =D63+D72+D78 -> 19162.7 | E81: =E63+E72+E78 -> 21678.346 | F81: =F63+F72+F78 -> 23670.508 | G81: =G63+G72+G78 -> 26294.167 | H81: =H63+H72+H78 -> 29159.361 | I81: =I63+I72+I78 -> 32286.726
A85: Starbucks: Store Operating Data: | E85: Starbucks: Revenue Forecasts by Segment and Type
A87: Americas | B87: =B$19 -> 2013 | C87: =C$19 -> 2014 | D87: =D$19 -> 2015 | E87: =E$19 -> Year +1 | F87: =F$19 -> Year +2 | G87: =G$19 -> Year +3 | H87: =H$19 -> Year +4 | I87: =I$19 -> Year +5
A89: Net new stores opened during the year: | E89: Expectations for net new stores to be opened each year:
A90: Company-operated: | B90: 276 | C90: 317 | D90: 276 | E90: 350 | F90: 350 | G90: 350 | H90: 350 | I90: 350
A91: Licensed: | B91: 404 | C91: 381 | D91: 336 | E91: 350 | F91: 350 | G91: 350 | H91: 350 | I91: 350
A92: Total | B92: =B90+B91 -> 680 | C92: =C90+C91 -> 698 | D92: =D90+D91 -> 612 | E92: =E90+E91 -> 700 | F92: =F90+F91 -> 700 | G92: =G90+G91 -> 700 | H92: =H90+H91 -> 700 | I92: =I90+I91 -> 700
A94: Total stores
A95: Company-operated: | B95: 8078 | C95: 8395 | D95: 8671 | E95: =D95+E90 -> 9021 | F95: =E95+F90 -> 9371 | G95: =F95+G90 -> 9721 | H95: =G95+H90 -> 10071 | I95: =H95+I90 -> 10421
A96: Licensed: | B96: 5415 | C96: 5796 | D96: 6132 | E96: =D96+E91 -> 6482 | F96: =E96+F91 -> 6832 | G96: =F96+G91 -> 7182 | H96: =G96+H91 -> 7532 | I96: =H96+I91 -> 7882
A97: Total | B97: =B95+B96 -> 13493 | C97: =C95+C96 -> 14191 | D97: =D95+D96 -> 14803 | E97: =E95+E96 -> 15503 | F97: =F95+F96 -> 16203 | G97: =G95+G96 -> 16903 | H97: =H95+H96 -> 17603 | I97: =I95+I96 -> 18303
A99: Revenues:
A100: Company-operated: | B100: 10038.3 | C100: 10866.5 | D100: 11925.6 | E100: =E101*((D95+E95)/2) -> 13104.827 | F100: =F101*((E95+F95)/2) -> 14440.731 | G100: =G101*((F95+G95)/2) -> 15889.767 | H100: =H101*((G95+H95)/2) -> 17460.7 | I100: =I101*((H95+I95)/2) -> 19162.941
A101: Revenues per store/year: | B101: 1.2642695 | C101: =C100/((B95+C95)/2) -> 1.3193104 | D101: =D100/((C95+D95)/2) -> 1.3975858 | E101: =D101*(1+E102) -> 1.481441 | F101: =E101*(1+F102) -> 1.5703275 | G101: =F101*(1+G102) -> 1.6645471 | H101: =G101*(1+H102) -> 1.7644199 | I101: =H101*(1+I102) -> 1.8702851
A102: Growth rate: | C102: =C101/B101-1 -> 0.043535705 | D102: =D101/C101-1 -> 0.059330585 | E102: 0.06 | F102: 0.06 | G102: 0.06 | H102: 0.06 | I102: 0.06
A105: Licensed: | B105: 915.4 | C105: 1074.9 | D105: 1334.4 | E105: =E106*((D96+E96)/2) -> 1495.8123 | F105: =F106*((E96+F96)/2) -> 1673.55 | G105: =G106*((F96+G96)/2) -> 1867.2313 | H105: =H106*((G96+H96)/2) -> 2078.1295 | I105: =I106*((H96+I96)/2) -> 2307.6136
A106: Revenues per store/year: | B106: 0.17559946 | C106: =C105/((B96+C96)/2) -> 0.19175809 | D106: =D105/((C96+D96)/2) -> 0.22374245 | E106: =D106*(1+E107) -> 0.237167 | F106: =E106*(1+F107) -> 0.25139702 | G106: =F106*(1+G107) -> 0.26648084 | H106: =G106*(1+H107) -> 0.28246969 | I106: =H106*(1+I107) -> 0.29941788
A107: Growth rate: | C107: =C106/B106-1 -> 0.092019825 | D107: =D106/C106-1 -> 0.16679536 | E107: =E102 -> 0.06 | F107: =F102 -> 0.06 | G107: =G102 -> 0.06 | H107: =H102 -> 0.06 | I107: =I102 -> 0.06
A110: CAP | B110: =B$19 -> 2013 | C110: =C$19 -> 2014 | D110: =D$19 -> 2015 | E110: =E$19 -> Year +1 | F110: =F$19 -> Year +2 | G110: =G$19 -> Year +3 | H110: =H$19 -> Year +4 | I110: =I$19 -> Year +5
A112: Net new stores opened during the year: | E112: Expectations for net new stores to be opened each year:
A113: Company-operated: | B113: 239 | C113: 250 | D113: 1320 | E113: 300 | F113: 300 | G113: 300 | H113: 300 | I113: 300
A114: Licensed: | B114: 349 | C114: 492 | D114: -482 | E114: 600 | F114: 600 | G114: 600 | H114: 600 | I114: 600
A115: Total | B115: =B113+B114 -> 588 | C115: =C113+C114 -> 742 | D115: =D113+D114 -> 838 | E115: =E113+E114 -> 900 | F115: =F113+F114 -> 900 | G115: =G113+G114 -> 900 | H115: =H113+H114 -> 900 | I115: =I113+I114 -> 900
A117: Total stores
A118: Company-operated: | B118: 882 | C118: 1132 | D118: 2452 | E118: =D118+E113 -> 2752 | F118: =E118+F113 -> 3052 | G118: =F118+G113 -> 3352 | H118: =G118+H113 -> 3652 | I118: =H118+I113 -> 3952
A119: Licensed: | B119: 3000 | C119: 3492 | D119: 3010 | E119: =D119+E114 -> 3610 | F119: =E119+F114 -> 4210 | G119: =F119+G114 -> 4810 | H119: =G119+H114 -> 5410 | I119: =H119+I114 -> 6010
A120: Total | B120: =B118+B119 -> 3882 | C120: =C118+C119 -> 4624 | D120: =D118+D119 -> 5462 | E120: =E118+E119 -> 6362 | F120: =F118+F119 -> 7262 | G120: =G118+G119 -> 8162 | H120: =H118+H119 -> 9062 | I120: =I118+I119 -> 9962
A122: Revenues:
A123: Company-operated: | B123: 671.7 | C123: 859.4 | D123: 2127.3 | E123: =E124*((D118+E118)/2) -> 2579.012 | F123: =F124*((E118+F118)/2) -> 3077.7069 | G123: =G124*((F118+G118)/2) -> 3633.5819 | H123: =H124*((G118+H118)/2) -> 4252.1986 | I123: =I124*((H118+I118)/2) -> 4939.6172
A124: Revenues per store/year: | B124: 0.88091803 | C124: =C123/((B118+C118)/2) -> 0.85342602 | D124: =D123/(C118+1009+((D113-1009)/2)) -> 0.92632266 | E124: =D124*(1+E125) -> 0.99116525 | F124: =E124*(1+F125) -> 1.0605468 | G124: =F124*(1+G125) -> 1.1347851 | H124: =G124*(1+H125) -> 1.2142201 | I124: =H124*(1+I125) -> 1.2992155
A125: Growth rate: | C125: =C124/B124-1 -> -0.031208369 | D125: =D124/C124-1 -> 0.085416481 | E125: 0.07 | F125: 0.07 | G125: 0.07 | H125: 0.07 | I125: 0.07
A128: Licensed: | B128: 245.3 | C128: 270.2 | D128: 264.4 | E128: =E129*((D119+E119)/2) -> 340.9523 | F128: =F129*((E119+F119)/2) -> 430.94928 | G128: =G129*((F119+G119)/2) -> 531.87518 | H128: =H129*((G119+H119)/2) -> 644.81905 | I128: =I129*((H119+I119)/2) -> 770.96887
A129: Revenues per store/year: | B129: 0.086816493 | C129: =C128/((B119+C119)/2) -> 0.083240912 | D129: =D128/(C119-1009+((D114+1009)/2)) -> 0.096267977 | E129: =D129*(1+E130) -> 0.10300674 | F129: =E129*(1+F130) -> 0.11021721 | G129: =F129*(1+G130) -> 0.11793241 | H129: =G129*(1+H130) -> 0.12618768 | I129: =H129*(1+I130) -> 0.13502082
A130: Growth rate: | C130: =C129/B129-1 -> -0.041185501 | D130: =D129/C129-1 -> 0.15649835 | E130: 0.07 | F130: 0.07 | G130: 0.07 | H130: 0.07 | I130: 0.07
A134: EMEA | B134: =B$19 -> 2013 | C134: =C$19 -> 2014 | D134: =D$19 -> 2015 | E134: =E$19 -> Year +1 | F134: =F$19 -> Year +2 | G134: =G$19 -> Year +3 | H134: =H$19 -> Year +4 | I134: =I$19 -> Year +5
A136: Net new stores opened during the year: | E136: Expectations for net new stores to be opened each year:
A137: Company-operated: | B137: -29 | C137: -9 | D137: -80 | E137: 0 | F137: 0 | G137: 0 | H137: 0 | I137: 0
A138: Licensed: | B138: 129 | C138: 180 | D138: 302 | E138: 200 | F138: 200 | G138: 200 | H138: 200 | I138: 200
A139: Total | B139: =B137+B138 -> 100 | C139: =C137+C138 -> 171 | D139: =D137+D138 -> 222 | E139: =E137+E138 -> 200 | F139: =F137+F138 -> 200 | G139: =G137+G138 -> 200 | H139: =H137+H138 -> 200 | I139: =I137+I138 -> 200
A141: Total stores
...

Sheet Valuation
A1: =Data!A1 -> Financial Statement Analysis Package (FSAP): Version 9.0
A2: =Data!A2 -> Financial Reporting, Financial Statement Analysis, and Valuation: A Strategic Perspective, 9th Edition | L2: FSAP User Guides:
A3: By James Wahlen, Steve Baginski and Mark Bradshaw
L4: The FSAP user should only enter data in the blue-font cells shaded light green.
A6: The FSAP User Guides appear in column L to the right. | L6: A Comment on Entering Valuation Parameter Assumptions:
L7: The FSAP user must enter valuation parameter assumptions in the green-shaded, blue font boxes below. These valuation parameters involve the costs of common equity capital, debt capital, and preferred stock capital (if any), as well as the long run growth rate assumption. FSAP references data in the Data spreadsheet and the Forecasts spreadsheet when available. FSAP uses these parameters to compute costs of capital to use as discount rates in the valuation models.
A8: DATA CHECKS - Estimated Value per Share
A9: Dividend Based Valuation | F9: =E83 -> 66.096015 | L9: FSAP automatically references the estimated value per share.
A10: Free Cash Flow Valuation | F10: =E113 -> 66.096015 | L10: FSAP automatically references the estimated value per share.
A11: Residual Income Valuation | F11: =E170 -> 66.096015 | L11: FSAP automatically references the estimated value per share.
A12: Residual Income Market-to-Book Valuation | F12: =E231 -> 66.096015 | L12: FSAP automatically references the estimated value per share.
A13: Free Cash Flow for All Debt and Equity Valuation | F13: =E267 -> 65.953759 | L13: FSAP automatically references the estimated value per share.
A14: Check: All Estimated Value per Share amounts should be the same, with the possible exception of the share value from the
A15: Free Cash Flow for All Debt and Equity model. See additional comments in cell L266.
A18: FSAP OUTPUT: | C18: VALUATION MODELS
A19: =Data!$A$9 -> Analyst Name: | C19: =Data!$B$9 -> Wahlen, Baginski & Bradshaw
A20: =Data!$A$10 -> Company Name: | C20: =Data!$B$10 -> Starbucks
A22: VALUATION PARAMETER ASSUMPTIONS
L23: Market Value Parameters:
A24: Current share price | F24: =Data!G150 -> 56.84 | L24: FSAP uses the most recent share price entered in the Data spreadsheet. The FSAP user can override this and enter the most recent share price directly in this cell.
A25: Number of shares outstanding | F25: =Data!$G$147 -> 1485.1 | L25: FSAP uses the most recent number of shares outstanding entered in the Data spreadsheet. The FSAP user can override this and enter the most recent number of shares outstanding directly in this cell.
A26: Current market value | F26: =F24*F25 -> 84413.084 | L26: FSAP computes market value of equity using market price per share times number of shares outstanding.
A28: Long-run growth assumption used in forecasts | F28: =Forecasts!$J$15 -> 0.03 | L28: Long Run Growth Parameters:
A29: Long-run growth assumption used in valuation. | F29: 0.03 | L29: Enter the long run growth rate assumption for use in the valuation models. This growth rate must agree with the long run growth rate used to forecast Year +6 and Beyond in the Forecasts spreadsheet.
A30: (Both long-run growth assumptions should be the same.)
A32: COST OF EQUITY CAPITAL: | L32: Cost of Equity Capital Parameters:
A33: Equity risk factor (market beta) | F33: 0.75 | L33: Enter the market beta.
A34: Risk free rate | F34: 0.027 | L34: Enter a risk-free rate of return, such as the yield on 3 to 5 year U.S. Treasury bonds.
A35: Market risk premium | F35: 0.06 | L35: Enter the expected market risk premium. This is the amount by which the average expected rate of return on a diversified portfolio of stocks is expected to exceed the expected rate of return on a portfolio of risk free securities. Reasonable estimates commonly range from 3% to 9%.
A36: Required rate of return on common equity: | F36: =F34+F33*F35 -> 0.072 | L36: Using the above parameters, FSAP computes the expected rate of return on equity using the market model version of the CAPM.
A38: COST OF DEBT CAPITAL | L38: Cost of Debt Capital Parameters:
A39: Debt capital | F39: 2402 | L39: FSAP uses the total amount of short term debt and long term debt from the most recent balance sheet data in the Forecasts worksheet. The analyst can override this default by entering the market value of debt capital, if known.
A40: Cost of debt capital, before tax | F40: =-Forecasts!E63 -> 0.027067164 | L40: FSAP uses the interest rate assumption entered in the Forecasts spreadsheet. The analyst can override this default by entering here the expected interest rate on debt capital to be used in computing the weighted average cost of capital. The interest rate on debt capital used here in valuation should be consistent with the interest rate assumed in the forecasts of future interest expense in the Forecasts Spreadsheet.
A41: Effective tax rate | F41: =Forecasts!E76 -> -0.34 | L41: FSAP uses the tax rate assumption entered in the Forecasts spreadsheet. The analyst can override this default by entering here the effective tax rate for use in computing the effective after-tax cost of debt capital.
A42: After-tax cost of debt capital | F42: =F40*(1+F41) -> 0.017864328 | L42: FSAP uses the above parameters to compute the after-tax cost of debt capital.
A44: COST OF PREFERRED STOCK | L44: Cost of Preferred Stock Parameters:
A45: Preferred stock capital | F45: 0 | L45: FSAP uses the amount of preferred stock entered in the most recent balance sheet data in the Forecasts worksheet. The analyst can override this default by entering the market value of preferred stock, if known.
A46: Preferred dividends | F46: 0 | L46: FSAP uses the preferred stock dividend entered in the Forecasts spreadsheet. The analyst can override this default by entering the required rate of return on preferred stock, if known.
A47: Implied yield | F47: 0 | L47: FSAP uses the above parameters to compute the cost of preferred stock capital.
A49: COST OF NONCONTROLLING INTERESTS' CAPITAL | L49: Cost of Noncontrolling Interests Parameters:
A50: Noncontrolling interests capital | F50: 0 | L50: FSAP uses the amount of equity capital attributable to noncontrolling interests entered in the most recent balance sheet data in the Forecasts worksheet. The analyst can override this default by entering the market value of noncontrolling interests, if known.
A51: Earnings attributable to noncontrolling interests | F51: 0 | L51: FSAP uses the earnings attributable to noncontrolling interests entered in the Forecasts spreadsheet. The analyst can override this default by entering the required rate of return on noncontrolling interests, if known.
A52: Implied yield | F52: 0 | L52: FSAP uses the above parameters to compute the cost of capital atttributable to noncontrolling interests.
A54: WEIGHTED AVERAGE COST OF CAPITAL | L54: Weighted Average Cost of Capital:
A55: Weight of equity in capital structure | F55: =$F$26/($F$26+$F$39+$F$45+$F$50) -> 0.972332 | L55: FSAP computes the weight of equity in the capital structure by dividing the market value of equity by the market value of total capital (common equity, debt, preferred stock, and noncontrolling interests).
A56: Weight of debt in capital structure | F56: =$F$39/($F$26+$F$39+$F$45+$F$50) -> 0.027668003 | L56: FSAP computes the weight of debt in the capital structure by dividing the value of debt by the market value of total capital (common equity, debt, preferred stock, and noncontrolling interests).
A57: Weight of preferred in capital structure | F57: =$F$45/($F$26+$F$39+$F$45+$F$50) -> 0 | L57: FSAP computes the weight of preferred stock in the capital structure by dividing the market value of preferred by the market value of total capital (common equity, debt, preferred stock, and noncontrolling interests).
A58: Weight of noncontrolling interests in capital structure | F58: =$F$50/($F$26+$F$39+$F$45+$F$50) -> 0 | L58: FSAP computes the weight of noncontrolling interests in the capital structure by dividing the book value of noncontrolling interests by the market value of total capital (common equity, debt, preferred stock, and noncontrolling interests).
A59: Weighted average cost of capital | F59: =($F$55*$F$36)+($F$56*F42)+($F$57*$F$47)+($F$58*$F$52) -> 0.070502174 | L59: FSAP uses the above weights and costs of capital to compute a weighted average cost of capital.
A63: FSAP OUTPUT: | C63: =C18 -> VALUATION MODELS
A64: =Data!$A$9 -> Analyst Name: | C64: =Data!$B$9 -> Wahlen, Baginski & Bradshaw
A65: =Data!$A$10 -> Company Name: | C65: =Data!$B$10 -> Starbucks
J66: Continuing
E67: 1 | F67: 2 | G67: 3 | H67: 4 | I67: 5 | J67: Value | L67: Dividends-Based Valuation:
A68: Dividends-Based Valuation | E68: Year +1 | F68: Year +2 | G68: Year +3 | H68: Year +4 | I68: Year +5 | J68: Year +6 | L68: Chapter 11 describes the dividends-based valuation approach.
A70: Dividends Paid to Common Shareholders | E70: =-Forecasts!E258-Forecasts!E255 -> 1187.5788 | F70: =-Forecasts!F258-Forecasts!F255 -> 1309.2437 | G70: =-Forecasts!G258-Forecasts!G255 -> 1483.2373 | H70: =-Forecasts!H258-Forecasts!H255 -> 1674.3995 | I70: =-Forecasts!I258-Forecasts!I255 -> 2080.3673 | L70: FSAP uses implied dividends for common shareholders from the Forecasts worksheet.
A71: Less: Common Stock Issues | E71: =Forecasts!D222-Forecasts!E222 -> -1.3104867 | F71: =Forecasts!E222-Forecasts!F222 -> -2.4337548 | G71: =Forecasts!F222-Forecasts!G222 -> -3.2699927 | H71: =Forecasts!G222-Forecasts!H222 -> -3.7719982 | I71: =Forecasts!H222-Forecasts!I222 -> -6.6898733 | L71: FSAP uses the change in common stock plus paid in capital from the Forecasts worksheet. Stock issues are treated as negative dividends.
A72: Plus: Common Stock Repurchases | E72: =-Forecasts!E268 -> 2653.6743 | F72: =-Forecasts!F268 -> 1483.5488 | G72: =-Forecasts!G268 -> 1598.2211 | H72: =-Forecasts!H268 -> 1757.6045 | I72: =-Forecasts!I268 -> 1509.9021 | L72: FSAP uses the change in treasury stock from the Forecasts worksheet. Purchases of treasury stock are treated as dividends.
A73: Dividends to Common Equity | E73: =SUM(E70:E72) -> 3839.9427 | F73: =SUM(F70:F72) -> 2790.3587 | G73: =SUM(G70:G72) -> 3078.1884 | H73: =SUM(H70:H72) -> 3428.232 | I73: =SUM(I70:I72) -> 3583.5796 | J73: =(Forecasts!J97-Forecasts!J255)-(Forecasts!J222+Forecasts!J225+Forecasts!J228+Forecasts!J231-Forecasts!I222-Forecasts!I225-Forecasts!I228-Forecasts!I231) -> 4822.9127 | L73: These figures represent the forecasted total dividends to common equity shareholders.
A75: Present Value Factors | E75: =1/(1+$F$36)^E67 -> 0.93283582 | F75: =1/(1+$F$36)^F67 -> 0.87018267 | G75: =1/(1+$F$36)^G67 -> 0.81173756 | H75: =1/(1+$F$36)^H67 -> 0.75721788 | I75: =1/(1+$F$36)^I67 -> 0.70635996 | L75: These present value factors are based on the equity cost of capital, computed above.
A76: Present Value Net Dividends | E76: =E73*E75 -> 3582.0361 | F76: =F73*F75 -> 2428.1218 | G76: =G73*G75 -> 2498.6812 | H76: =H73*H75 -> 2595.9186 | I76: =I73*I75 -> 2531.2971
A77: Sum of Present Value Net Dividends | E77: =SUM(E76:I76) -> 13636.055 | L77: The sum of the present value of net dividends through Year +5.
A78: Present Value of Continuing Value | E78: =J73/($F$36-$F$29)*$I$75 -> 81112.2 | L78: The present value of continuing value dividends in Year +6 and beyond. Year +6 dividends are treated as a perpetuity with growth using the long-run growth rate assumption, discounted to present value at the equity cost of capital.
A79: Total | E79: =E77+E78 -> 94748.255
A80: Adjust to midyear discounting | E80: =(1+$F$36/2) -> 1.036 | L80: This adjustment corrects for over-discounting. The present value factors discount from the end of each year to the present, whereas dividends, cash flows, and earnings are generated throughout the year. This adjustment computes the present value so that dividends, cash flows, and earnings are discounted from the mid-point of each year.
A81: Total Present Value Dividends | E81: =E79*E80 -> 98159.192
A82: Shares Outstanding | E82: =$F$25 -> 1485.1
A83: Estimated Value per Share | E83: =E81/E82 -> 66.096015 | L83: The estimated value per share.
A85: Current share price | E85: =$F$24 -> 56.84
A86: Percent difference | E86: =E83/E85-1 -> 0.16284334 | L86: (Value/price)-1: positive number indicates underpricing.
U89: =1/(0.042) -> 23.809524
A90: FSAP OUTPUT: | C90: =C18 -> VALUATION MODELS | U90: =U89*J103 -> 114831.25
A91: =Data!$A$9 -> Analyst Name: | C91: =Data!$B$9 -> Wahlen, Baginski & Bradshaw | L91: =E97+E98 -> 4396.7417 | M91: =F97+F98 -> 4452.8714 | N91: =G97+G98 -> 5048.5834 | O91: =H97+H98 -> 5706.896 | P91: =I97+I98 -> 6170.9186 | Q91: =J97+J98 -> 5411.084
A92: =Data!$A$10 -> Company Name: | C92: =Data!$B$10 -> Starbucks
J93: Continuing
E94: 1 | F94: 2 | G94: 3 | H94: 4 | I94: 5 | J94: Value | L94: Free Cash Flows for Common Equity Valuation:
A95: Free Cash Flows for Common Equity | E95: Year +1 | F95: Year +2 | G95: Year +3 | H95: Year +4 | I95: Year +5 | J95: Year +6 | L95: Chapter 12 describes the free cash flows-based valuation approaches.
A97: Net Cash Flow from Operations | E97: =Forecasts!E297 -> 4648.4936 | F97: =Forecasts!F297 -> 4616.6107 | G97: =Forecasts!G297 -> 5264.2265 | H97: =Forecasts!H297 -> 5942.3914 | I97: =Forecasts!I297 -> 6427.9623 | J97: =Forecasts!J297 -> 5490.6951 | L97: FSAP uses net cash flows from operations from the Forecasts worksheet.
A98: Decrease (Increase) in Cash Required for Operations | E98: =-Forecasts!E315 -> -251.7519 | F98: =-Forecasts!F315 -> -163.73931 | G98: =-Forecasts!G315 -> -215.64318 | H98: =-Forecasts!H315 -> -235.49543 | I98: =-Forecasts!I315 -> -257.04368 | J98: =-Forecasts!J315 -> -79.611105 | L98: The analyst should adjust free cash flows for changes in cash required for operations. As firms grow, they typically require larger cash balances for liquidity in operating activities. FSAP is programmed to automatically adjust free cash flows for the change in the cash balance, which is assumed to be required for operations.
A99: Net Cash Flow from Investing | E99: =Forecasts!E305 -> -1554.999 | F99: =Forecasts!F305 -> -1662.5127 | G99: =Forecasts!G305 -> -1970.3949 | H99: =Forecasts!H305 -> -2278.664 | I99: =Forecasts!I305 -> -2587.339 | J99: =Forecasts!J305 -> -688.59629 | L99: FSAP uses net cash flows from investing from the Forecasts worksheet.
A100: Net CFs from Debt Financing | E100: =Forecasts!E306+Forecasts!E307 -> 1000 | F100: =Forecasts!F306+Forecasts!F307 -> 0 | G100: =Forecasts!G306+Forecasts!G307 -> 0 | H100: =Forecasts!H306+Forecasts!H307 -> 0 | I100: =Forecasts!I306+Forecasts!I307 -> 0 | J100: =Forecasts!J306+Forecasts!J307 -> 100.425 | L100: FSAP uses net cash flows from debt financing from the Forecasts worksheet.
A101: Net CFs into Financial Assets | E101: =-E252 -> 0 | F101: =-F252 -> 0 | G101: =-G252 -> 0 | H101: =-H252 -> 0 | I101: =-I252 -> 0 | J101: =-J252 -> 0 | L101: This row enables the analyst to adjust for any investing cash flows that should be classified as financing cash flows. For example, if the investing cash flows include cash outflows to acquire investment securities that will be used to retire debt, then these cash outflows should be added back in computing free cash flows to debt and equity.
A102: Net CFs - Pref. Stock and Noncontrolling Interests | E102: =Forecasts!E308-Forecasts!E255+Forecasts!E313 -> -1.8 | F102: =Forecasts!F308-Forecasts!F255+Forecasts!F313 -> 0 | G102: =Forecasts!G308-Forecasts!G255+Forecasts!G313 -> 0 | H102: =Forecasts!H308-Forecasts!H255+Forecasts!H313 -> 0 | I102: =Forecasts!I308-Forecasts!I255+Forecasts!I313 -> 0 | J102: =Forecasts!J308-Forecasts!J255+Forecasts!J313 -> 0 | L102: FSAP uses net cash flows from preferred stock and minority interests from the Forecasts worksheet.
A103: Free Cash Flow for Common Equity | E103: =SUM(E97:E102) -> 3839.9427 | F103: =SUM(F97:F102) -> 2790.3587 | G103: =SUM(G97:G102) -> 3078.1884 | H103: =SUM(H97:H102) -> 3428.232 | I103: =SUM(I97:I102) -> 3583.5796 | J103: =SUM(J97:J102) -> 4822.9127 | L103: These figures represent the forecasted total free cash flows to common equity shareholders.
A105: Present Value Factors | E105: =1/(1+$F$36)^E94 -> 0.93283582 | F105: =1/(1+$F$36)^F94 -> 0.87018267 | G105: =1/(1+$F$36)^G94 -> 0.81173756 | H105: =1/(1+$F$36)^H94 -> 0.75721788 | I105: =1/(1+$F$36)^I94 -> 0.70635996 | L105: These present value factors are based on the equity cost of capital, computed above.
A106: Present Value Free Cash Flows | E106: =E103*E105 -> 3582.0361 | F106: =F103*F105 -> 2428.1218 | G106: =G103*G105 -> 2498.6812 | H106: =H103*H105 -> 2595.9186 | I106: =I103*I105 -> 2531.2971
A107: Sum of Present Value Free Cash Flows | E107: =SUM(E106:I106) -> 13636.055 | L107: The sum of the present value of free cash flows for common equity shareholders through Year +5.
A108: Present Value of Continuing Value | E108: =J103/($F$36-$F$29)*I105 -> 81112.2 | L108: The present value of continuing free cash flows in Year +6 and beyond. Year +6 free cash flows are treated as a perpetuity with growth using the long-run growth rate assumption, discounted to present value at the equity cost of capital.
A109: Total | E109: =E107+E108 -> 94748.255
A110: Adjust to midyear discounting | E110: =(1+$F$36/2) -> 1.036 | L110: This adjustment corrects for over-discounting. The present value factors discount from the end of each year to the present, whereas dividends, cash flows, and earnings are generated throughout the year. This adjustment computes the present value so that dividends, cash flows, and earnings are discounted from the mid-point of each year.
A111: Total Present Value Free Cash Flows to Equity | E111: =E109*E110 -> 98159.192
A112: Shares Outstanding | E112: =$F$25 -> 1485.1
A113: Estimated Value per Share | E113: =E111/E112 -> 66.096015 | L113: The estimated value per share.
A115: Current share price | E115: =$F$24 -> 56.84
A116: Percent difference | E116: =E113/E115-1 -> 0.16284334 | L116: (Value/price)-1: positive number indicates underpricing.
A120: FSAP OUTPUT: | C120: =C18 -> VALUATION MODELS
A121: =Data!$A$9 -> Analyst Name: | C121: =Data!$B$9 -> Wahlen, Baginski & Bradshaw
A122: =Data!$A$10 -> Company Name: | C122: =Data!$B$10 -> Starbucks
A124: Dividends Valuation Sensitivity Analysis:
C126: Long-Run Growth Assumptions | L126: Sensitivity Analyses:
...
